Workbook

Sheet 00_README
A1: National Grid PLC
A2: FP&A, Three-Statement Financial Model & Valuation Case Study
A4: Model Version | B4: 1
A5: Last updated | B5: 46270
A6: Reporting currency | B6: GBP (£m unless otherwise stated)
A7: Historical period | B7: FY2024A - FY2026A
A8: Forecast Period | B8: FY2027E - FY2031E
A9: Fiscal Year End | B9: 46112
A11: Model Objective | B11: Build an integrated FP&A and financial modelling case study for National Grid plc using publicly available financial information. The model analyses historical performance, forecasts earnings and cash flows using business-specific operating drivers, models capital investment and financing requirements, evaluates scenarios and sensitivities, and presents key outputs through a management dashboard.
A14: Core model outputs | B14: Historical three-statement analysis
B15: Revenue and operating profit forecasting
B16: Segment analysis
B17: Capital investment and PP&E schedule
B18: Working capital forecasting
B19: Debt and interest schedule
B20: Free cash flow analysis
B21: Actual vs Budget vs Forecast analysis
B22: KPI and ratio analysis
B23: Base / Upside / Downside scenarios
B24: DCF valuation
B25: Sensitivity analysis
B26: Management dashboard
B27: Model integrity checks
A29: Modelling and formatting conventions
A30: Item | B30: Convention
A31: Hardcoded inputs | B31: Blue font
A32: Formulas | B32: Black font
A33: Links to other worksheets | B33: Green font
A34: Key assumptions | B34: Blue font with pale yellow fill
A35: Negative values | B35: Display in brackets, e.g. (1,705)
A36: Zero values | B36: Display as (-)
A37: Financial units | B37: £m unless otherwise stated
A38: Historical years | B38: Marked with A
A39: Forecast years | B39: Marked with E

Sheet 01_CONTROL
A1: NATIONAL GRID PLC — MODEL CONTROL
A4: Active Scenario | B4: Base | D4: Base | H4: 2026
A5: Reporting Currency | B5: GBP | D5: Upside
A6: Financial Units | B6: £m | D6: Dowside
A7: Last Historical Year | B7: 2026
A8: Forecast start year | B8: 2027
A9: Forecast end year | B9: 2031

Sheet 02_RAW_DATA
A1: NATIONAL GRID PLC — RAW FINANCIAL DATA
A3: Primary Source | B3: National Grid plc Annual Report and Accounts 2025/26
A4: Reporting Currency | B4: £m unless otherwise stated
A6: CONSOLIDATED INCOME STATEMENT
A7: Income Statement (£m) | B7: FY2024A | C7: FY2025A | D7: FY2026A
A8: Revenue | B8: 19850 | C8: 18378 | D8: 17687
A9: Impairment losses on financial assets | B9: -179 | C9: -200 | D9: -243
A10: Other operating costs | B10: -15208 | C10: -13244 | D10: -12502
A11: Other operating income | B11: 12 | C11: 0 | D11: 489
A12: Operating profit | B12: 4475 | C12: 4934 | D12: 5431
A13: Finance income | B13: 248 | C13: 450 | D13: 380
A14: Finance costs | B14: -1712 | C14: -1807 | D14: -1705
A15: Share of JV & associate results | B15: 37 | C15: 73 | D15: 76
A16: Profit before tax | B16: 3048 | C16: 3650 | D16: 4182
A17: Tax | B17: -831 | C17: -821 | D17: -939
A18: Profit after tax – continuing operations | B18: 2217 | C18: 2829 | D18: 3243
A19: Profit after tax – discontinued operations | B19: 74 | C19: 76 | D19: 0
A20: Total profit for the year | B20: 2291 | C20: 2905 | D20: 3243
A23: CONSOLIDATED BALANCE SHEET
A24: Balance Sheet | B24: FY2024A | C24: FY2025A | D24: FY2026A
A25: ASSETS
A26: Non-Current Assets
A27: Goodwill | B27: 9729 | C27: 9532 | D27: 9417
A28: Other intangible assets | B28: 3431 | C28: 3564 | D28: 3879
A29: Property, plant & equipment | B29: 68907 | C29: 74091 | D29: 81520
A30: Other non-current assets | B30: 848 | C30: 959 | D30: 1384
A31: Pension assets | B31: 2407 | C31: 2489 | D31: 2507
A32: Financial & other investments | B32: 880 | C32: 798 | D32: 842
A33: Investments in JV & associates | B33: 1420 | C33: 608 | D33: 624
A34: Derivative financial assets – non-current | B34: 324 | C34: 369 | D34: 623
A35: Total non-current assets | B35: 87946 | C35: 92410 | D35: 100796
A36: Current Assets
A37: Inventories | B37: 828 | C37: 557 | D37: 559
A38: Trade & other receivables | B38: 3415 | C38: 4092 | D38: 3867
A39: Current tax assets | B39: 11 | C39: 11 | D39: 16
A40: Financial & other investments – current | B40: 3699 | C40: 5753 | D40: 2453
A41: Derivative financial assets – current | B41: 44 | C41: 113 | D41: 215
A42: Cash & cash equivalents | B42: 559 | C42: 1178 | D42: 375
A43: Assets held for sale | B43: 1823 | C43: 2628 | D43: 0
A44: Total current assets | B44: 10379 | C44: 14332 | D44: 7485
A45: TOTAL ASSETS | B45: 98325 | C45: 106742 | D45: 108281
A47: LIABILITIES
A48: Current Liabilities
A49: Current borrowings | B49: -4859 | C49: -4662 | D49: -3900
A50: Derivative financial liabilities – current | B50: -335 | C50: -381 | D50: -268
A51: Trade & other payables | B51: -4076 | C51: -4472 | D51: -5049
A52: Contract liabilities – current | B52: -127 | C52: -96 | D52: -110
A53: Current tax liabilities | B53: -220 | C53: -219 | D53: -45
A54: Provisions – current | B54: -298 | C54: -357 | D54: -425
A55: Liabilities held for sale | B55: -1474 | C55: -434 | D55: 0
A56: Total current liabilities | B56: -11389 | C56: -10621 | D56: -9797
A57: Non-Current Liabilities
A58: Non-current borrowings | B58: -42213 | C58: -42877 | D58: -42855
A59: Derivative financial liabilities – non-current | B59: -909 | C59: -821 | D59: -750
A60: Other non-current liabilities | B60: -880 | C60: -876 | D60: -1114
A61: Contract liabilities – non-current | B61: -2119 | C61: -2418 | D61: -2699
A62: Deferred tax liabilities | B62: -7519 | C62: -8038 | D62: -9040
A63: Pension obligations | B63: -593 | C63: -573 | D63: -360
A64: Provisions – non-current | B64: -2811 | C64: -2692 | D64: -2336
A65: Total non-current liabilities | B65: -57044 | C65: -58295 | D65: -59154
A66: TOTAL LIABILITIES | B66: -68433 | C66: -68916 | D66: -68951
A68: Net Assets | B68: =29892 -> 29892 | C68: =37826 -> 37826 | D68: =39330 -> 39330
A70: EQUITY
A71: Share capital | B71: 493 | C71: 638 | D71: 647
A72: Share premium account | B72: 1298 | C72: 1292 | D72: 1285
A73: Retained earnings | B73: 32066 | C73: 40106 | D73: 41909
A74: Other equity reserves | B74: -3990 | C74: -4233 | D74: -4542
A75: Total shareholders' equity | B75: 29867 | C75: 37803 | D75: 39299
A76: Non-controlling interests | B76: 25 | C76: 23 | D76: 31
A77: TOTAL EQUITY | B77: 29892 | C77: 37826 | D77: 39330
A80: CONSOLIDATED CASH FLOW STATEMENT
A81: Cash Flow Statement (£) | B81: FY2024A | C81: FY2025A | D81: FY2026A
A82: OPERATING ACTIVITIES
A83: Operating profit – continuing operations | B83: 4475 | C83: 4934 | D83: 5431
A84: Exceptional items and remeasurements | B84: 987 | C84: -169 | D84: -387
A85: Other fair value movements | B85: -16 | C85: 66 | D85: -31
A86: Depreciation, amortisation & impairment | B86: 2061 | C86: 2175 | D86: 2247
A87: Share-based payments | B87: 37 | C87: 37 | D87: 45
A88: Changes in working capital | B88: -49 | C88: 104 | D88: 759
A89: Changes in provisions | B89: -154 | C89: 10 | D89: -127
A90: Changes in pensions & post-retirement obligations | B90: 31 | C90: -90 | D90: -31
A91: Cash flows relating to exceptional items | B91: -91 | C91: -76 | D91: -45
A92: Cash generated from operations | B92: 7281 | C92: 6991 | D92: 7861
A93: Tax paid | B93: -342 | C93: -183 | D93: -32
A94: Net cash inflow from operating activities | B94: 6939 | C94: 6808 | D94: 7829
A96: INVESTING ACTIVITIES
A97: Purchases of intangible assets | B97: -549 | C97: -526 | D97: -586
A98: Purchases of property, plant & equipment | B98: -6904 | C98: -8780 | D98: -9989
A99: Disposals of PP&E | B99: 52 | C99: 26 | D99: 68
A100: Investments in JV & associates | B100: -332 | C100: -396 | D100: -94
A101: Dividends received from JV, associates & other investments | B101: 176 | C101: 126 | D101: 105
A102: Disposal of UK Electricity System Operator | B102: 0 | C102: 577 | D102: 0
A103: Disposal of UK Gas Transmission interest | B103: 681 | C103: 686 | D103: 0
A104: Disposal of National Grid Renewables | B104: 0 | C104: 0 | D104: 1473
A105: Disposal of Grain LNG | B105: 0 | C105: 0 | D105: 1336
A106: Disposal of financial & other investments | B106: 102 | C106: 85 | D106: 67
A107: Acquisition of financial investments | B107: -81 | C107: -122 | D107: -67
A108: Contributions to National Grid Renewables & Emerald Energy Venture LLC | B108: -19 | C108: 0 | D108: 0
... A114: Net cash flow used in investing activities – continuing operations | B114: -7601 | C114: -10593 | D114: -4157
A116: FINANCING ACTIVITIES
...

Sheet 03_HIST_FS
A1: NATIONAL GRID PLC — HISTORICAL FINANCIAL STATEMENTS & ANALYSIS
A3: Historical Financials (£m) | B3: FY2024A | C3: FY2025A | D3: FY2026A
A5: INCOME STATEMENT
A6: Revenue | B6: ='02_RAW_DATA'!B8 -> 19850 | C6: ='02_RAW_DATA'!C8 -> 18378 | D6: ='02_RAW_DATA'!D8 -> 17687
A7: Revenue growth | C7: =C6/B6-1 -> -0.074156171 | D7: =D6/C6-1 -> -0.037599304
A8: Impairment losses on financial assets | B8: ='02_RAW_DATA'!B9 -> -179 | C8: ='02_RAW_DATA'!C9 -> -200 | D8: ='02_RAW_DATA'!D9 -> -243
A9: Other operating costs | B9: ='02_RAW_DATA'!B10 -> -15208 | C9: ='02_RAW_DATA'!C10 -> -13244 | D9: ='02_RAW_DATA'!D10 -> -12502
A10: Other operating income | B10: ='02_RAW_DATA'!B11 -> 12 | C10: ='02_RAW_DATA'!C11 -> 0 | D10: ='02_RAW_DATA'!D11 -> 489
A11: Operating profit | B11: =SUM(B6,B8:B10) -> 4475 | C11: =SUM(C6,C8:C10) -> 4934 | D11: =SUM(D6,D8:D10) -> 5431
A12: Operating margin | B12: =B11/B6 -> 0.22544081 | C12: =C11/C6 -> 0.26847317 | D12: =D11/D6 -> 0.30706168
A13: Finance income | B13: ='02_RAW_DATA'!B13 -> 248 | C13: ='02_RAW_DATA'!C13 -> 450 | D13: ='02_RAW_DATA'!D13 -> 380
A14: Finance costs | B14: ='02_RAW_DATA'!B14 -> -1712 | C14: ='02_RAW_DATA'!C14 -> -1807 | D14: ='02_RAW_DATA'!D14 -> -1705
A15: Share of JV & associate results | B15: ='02_RAW_DATA'!B15 -> 37 | C15: ='02_RAW_DATA'!C15 -> 73 | D15: ='02_RAW_DATA'!D15 -> 76
A16: Profit before tax | B16: =SUM(B11, B13:B15) -> 3048 | C16: =SUM(C11, C13:C15) -> 3650 | D16: =SUM(D11, D13:D15) -> 4182
A17: PBT margin | B17: =B16/B6 -> 0.15355164 | C17: =C16/C6 -> 0.19860703 | D17: =D16/D6 -> 0.23644485
A18: Tax | B18: ='02_RAW_DATA'!B17 -> -831 | C18: ='02_RAW_DATA'!C17 -> -821 | D18: ='02_RAW_DATA'!D17 -> -939
A19: Effective tax rate | B19: =-B18/B16 -> 0.2726378 | C19: =-C18/C16 -> 0.22493151 | D19: =-D18/D16 -> 0.22453372
A20: Profit after tax – continuing operations | B20: =SUM(B16,B18) -> 2217 | C20: =SUM(C16,C18) -> 2829 | D20: =SUM(D16,D18) -> 3243
A21: Profit after tax – discontinued operations | B21: ='02_RAW_DATA'!B19 -> 74 | C21: ='02_RAW_DATA'!C19 -> 76 | D21: ='02_RAW_DATA'!D19 -> 0
A22: Total profit for the year | B22: =SUM(B20:B21) -> 2291 | C22: =SUM(C20:C21) -> 2905 | D22: =SUM(D20:D21) -> 3243
A23: Net profit margin | B23: =B22/B6 -> 0.11541562 | C23: =C22/C6 -> 0.15806943 | D23: =D22/D6 -> 0.18335501
A26: BALANCE SHEET
A27: ASSETS
A28: Non-Current Assets
A29: Goodwill | B29: ='02_RAW_DATA'!B27 -> 9729 | C29: ='02_RAW_DATA'!C27 -> 9532 | D29: ='02_RAW_DATA'!D27 -> 9417
A30: Other intangible assets | B30: ='02_RAW_DATA'!B28 -> 3431 | C30: ='02_RAW_DATA'!C28 -> 3564 | D30: ='02_RAW_DATA'!D28 -> 3879
A31: Property, plant & equipment | B31: ='02_RAW_DATA'!B29 -> 68907 | C31: ='02_RAW_DATA'!C29 -> 74091 | D31: ='02_RAW_DATA'!D29 -> 81520
A32: Other non-current assets | B32: ='02_RAW_DATA'!B30 -> 848 | C32: ='02_RAW_DATA'!C30 -> 959 | D32: ='02_RAW_DATA'!D30 -> 1384
A33: Pension assets | B33: ='02_RAW_DATA'!B31 -> 2407 | C33: ='02_RAW_DATA'!C31 -> 2489 | D33: ='02_RAW_DATA'!D31 -> 2507
A34: Financial & other investments | B34: ='02_RAW_DATA'!B32 -> 880 | C34: ='02_RAW_DATA'!C32 -> 798 | D34: ='02_RAW_DATA'!D32 -> 842
A35: Investments in JV & associates | B35: ='02_RAW_DATA'!B33 -> 1420 | C35: ='02_RAW_DATA'!C33 -> 608 | D35: ='02_RAW_DATA'!D33 -> 624
A36: Derivative financial assets – non-current | B36: ='02_RAW_DATA'!B34 -> 324 | C36: ='02_RAW_DATA'!C34 -> 369 | D36: ='02_RAW_DATA'!D34 -> 623
A37: Total non-current assets | B37: =SUM(B29:B36) -> 87946 | C37: =SUM(C29:C36) -> 92410 | D37: =SUM(D29:D36) -> 100796
A38: Current Assets
A39: Inventories | B39: ='02_RAW_DATA'!B37 -> 828 | C39: ='02_RAW_DATA'!C37 -> 557 | D39: ='02_RAW_DATA'!D37 -> 559
A40: Trade & other receivables | B40: ='02_RAW_DATA'!B38 -> 3415 | C40: ='02_RAW_DATA'!C38 -> 4092 | D40: ='02_RAW_DATA'!D38 -> 3867
A41: Current tax assets | B41: ='02_RAW_DATA'!B39 -> 11 | C41: ='02_RAW_DATA'!C39 -> 11 | D41: ='02_RAW_DATA'!D39 -> 16
A42: Financial & other investments – current | B42: ='02_RAW_DATA'!B40 -> 3699 | C42: ='02_RAW_DATA'!C40 -> 5753 | D42: ='02_RAW_DATA'!D40 -> 2453
A43: Derivative financial assets – current | B43: ='02_RAW_DATA'!B41 -> 44 | C43: ='02_RAW_DATA'!C41 -> 113 | D43: ='02_RAW_DATA'!D41 -> 215
A44: Cash & cash equivalents | B44: ='02_RAW_DATA'!B42 -> 559 | C44: ='02_RAW_DATA'!C42 -> 1178 | D44: ='02_RAW_DATA'!D42 -> 375
A45: Assets held for sale | B45: ='02_RAW_DATA'!B43 -> 1823 | C45: ='02_RAW_DATA'!C43 -> 2628 | D45: ='02_RAW_DATA'!D43 -> 0
A46: Total current assets | B46: =SUM(B39:B45) -> 10379 | C46: =SUM(C39:C45) -> 14332 | D46: =SUM(D39:D45) -> 7485
A47: TOTAL ASSETS | B47: =B37+B46 -> 98325 | C47: =C37+C46 -> 106742 | D47: =D37+D46 -> 108281
A49: LIABILITIES
A50: Current Liabilities
A51: Current borrowings | B51: ='02_RAW_DATA'!B49 -> -4859 | C51: ='02_RAW_DATA'!C49 -> -4662 | D51: ='02_RAW_DATA'!D49 -> -3900
A52: Derivative financial liabilities – current | B52: ='02_RAW_DATA'!B50 -> -335 | C52: ='02_RAW_DATA'!C50 -> -381 | D52: ='02_RAW_DATA'!D50 -> -268
A53: Trade & other payables | B53: ='02_RAW_DATA'!B51 -> -4076 | C53: ='02_RAW_DATA'!C51 -> -4472 | D53: ='02_RAW_DATA'!D51 -> -5049
A54: Contract liabilities – current | B54: ='02_RAW_DATA'!B52 -> -127 | C54: ='02_RAW_DATA'!C52 -> -96 | D54: ='02_RAW_DATA'!D52 -> -110
A55: Current tax liabilities | B55: ='02_RAW_DATA'!B53 -> -220 | C55: ='02_RAW_DATA'!C53 -> -219 | D55: ='02_RAW_DATA'!D53 -> -45
A56: Provisions – current | B56: ='02_RAW_DATA'!B54 -> -298 | C56: ='02_RAW_DATA'!C54 -> -357 | D56: ='02_RAW_DATA'!D54 -> -425
A57: Liabilities held for sale | B57: ='02_RAW_DATA'!B55 -> -1474 | C57: ='02_RAW_DATA'!C55 -> -434 | D57: ='02_RAW_DATA'!D55 -> 0
A58: Total current liabilities | B58: =SUM(B51:B57) -> -11389 | C58: =SUM(C51:C57) -> -10621 | D58: =SUM(D51:D57) -> -9797
A59: Non-Current Liabilities
A60: Non-current borrowings | B60: ='02_RAW_DATA'!B58 -> -42213 | C60: ='02_RAW_DATA'!C58 -> -42877 | D60: ='02_RAW_DATA'!D58 -> -42855
A61: Derivative financial liabilities – non-current | B61: ='02_RAW_DATA'!B59 -> -909 | C61: ='02_RAW_DATA'!C59 -> -821 | D61: ='02_RAW_DATA'!D59 -> -750
A62: Other non-current liabilities | B62: ='02_RAW_DATA'!B60 -> -880 | C62: ='02_RAW_DATA'!C60 -> -876 | D62: ='02_RAW_DATA'!D60 -> -1114
A63: Contract liabilities – non-current | B63: ='02_RAW_DATA'!B61 -> -2119 | C63: ='02_RAW_DATA'!C61 -> -2418 | D63: ='02_RAW_DATA'!D61 -> -2699
A64: Deferred tax liabilities | B64: ='02_RAW_DATA'!B62 -> -7519 | C64: ='02_RAW_DATA'!C62 -> -8038 | D64: ='02_RAW_DATA'!D62 -> -9040
A65: Pension obligations | B65: ='02_RAW_DATA'!B63 -> -593 | C65: ='02_RAW_DATA'!C63 -> -573 | D65: ='02_RAW_DATA'!D63 -> -360
A66: Provisions – non-current | B66: ='02_RAW_DATA'!B64 -> -2811 | C66: ='02_RAW_DATA'!C64 -> -2692 | D66: ='02_RAW_DATA'!D64 -> -2336
A67: Total non-current liabilities | B67: =SUM(B60:B66) -> -57044 | C67: =SUM(C60:C66) -> -58295 | D67: =SUM(D60:D66) -> -59154
A68: TOTAL LIABILITIES | B68: =SUM(B58,B67) -> -68433 | C68: =SUM(C58,C67) -> -68916 | D68: =SUM(D58,D67) -> -68951
A70: Net Assets | B70: =B47+B68 -> 29892 | C70: =C47+C68 -> 37826 | D70: =D47+D68 -> 39330
A72: EQUITY
A73: Share capital | B73: ='02_RAW_DATA'!B71 -> 493 | C73: ='02_RAW_DATA'!C71 -> 638 | D73: ='02_RAW_DATA'!D71 -> 647
A74: Share premium account | B74: ='02_RAW_DATA'!B72 -> 1298 | C74: ='02_RAW_DATA'!C72 -> 1292 | D74: ='02_RAW_DATA'!D72 -> 1285
A75: Retained earnings | B75: ='02_RAW_DATA'!B73 -> 32066 | C75: ='02_RAW_DATA'!C73 -> 40106 | D75: ='02_RAW_DATA'!D73 -> 41909
A76: Other equity reserves | B76: ='02_RAW_DATA'!B74 -> -3990 | C76: ='02_RAW_DATA'!C74 -> -4233 | D76: ='02_RAW_DATA'!D74 -> -4542
A77: NCI | B77: ='02_RAW_DATA'!B76 -> 25 | C77: ='02_RAW_DATA'!C76 -> 23 | D77: ='02_RAW_DATA'!D76 -> 31
A78: Total shareholders' equity | B78: =SUM(B73:B76) -> 29867 | C78: =SUM(C73:C76) -> 37803 | D78: =SUM(D73:D76) -> 39299
A79: TOTAL EQUITY | B79: =SUM(B78,B77) -> 29892 | C79: =SUM(C78,C77) -> 37826 | D79: =SUM(D78,D77) -> 39330
A81: Balance sheet check | B81: =B47+B68-B79 -> 0 | C81: =C47+C68-C79 -> 0 | D81: =D47+D68-D79 -> 0
A84: CASH FLOW STATEMENT
B85: FY2024A | C85: FY2025A | D85: FY2026A
A86: OPERATING ACTIVITIES
A87: Operating profit | B87: =B11 -> 4475 | C87: =C11 -> 4934 | D87: =D11 -> 5431
A88: Exceptional items and remeasurements | B88: ='02_RAW_DATA'!B84 -> 987 | C88: ='02_RAW_DATA'!C84 -> -169 | D88: ='02_RAW_DATA'!D84 -> -387
A89: Other fair value movements | B89: ='02_RAW_DATA'!B85 -> -16 | C89: ='02_RAW_DATA'!C85 -> 66 | D89: ='02_RAW_DATA'!D85 -> -31
A90: Depreciation, amortisation & impairment | B90: ='02_RAW_DATA'!B86 -> 2061 | C90: ='02_RAW_DATA'!C86 -> 2175 | D90: ='02_RAW_DATA'!D86 -> 2247
A91: Share-based payments | B91: ='02_RAW_DATA'!B87 -> 37 | C91: ='02_RAW_DATA'!C87 -> 37 | D91: ='02_RAW_DATA'!D87 -> 45
A92: Changes in working capital | B92: ='02_RAW_DATA'!B88 -> -49 | C92: ='02_RAW_DATA'!C88 -> 104 | D92: ='02_RAW_DATA'!D88 -> 759
A93: Changes in provisions | B93: ='02_RAW_DATA'!B89 -> -154 | C93: ='02_RAW_DATA'!C89 -> 10 | D93: ='02_RAW_DATA'!D89 -> -127
A94: Changes in pensions & post-retirement obligations | B94: ='02_RAW_DATA'!B90 -> 31 | C94: ='02_RAW_DATA'!C90 -> -90 | D94: ='02_RAW_DATA'!D90 -> -31
A95: Cash flows relating to exceptional items | B95: ='02_RAW_DATA'!B91 -> -91 | C95: ='02_RAW_DATA'!C91 -> -76 | D95: ='02_RAW_DATA'!D91 -> -45
A96: Cash generated from operations | B96: =SUM(B87:B95) -> 7281 | C96: =SUM(C87:C95) -> 6991 | D96: =SUM(D87:D95) -> 7861
A97: Tax paid | B97: ='02_RAW_DATA'!B93 -> -342 | C97: ='02_RAW_DATA'!C93 -> -183 | D97: ='02_RAW_DATA'!D93 -> -32
A98: Net cash inflow from operating activities | B98: =SUM(B96:B97) -> 6939 | C98: =SUM(C96:C97) -> 6808 | D98: =SUM(D96:D97) -> 7829
A100: INVESTING ACTIVITIES
A101: Purchases of intangible assets | B101: ='02_RAW_DATA'!B97 -> -549 | C101: ='02_RAW_DATA'!C97 -> -526 | D101: ='02_RAW_DATA'!D97 -> -586
A102: Purchases of property, plant & equipment | B102: ='02_RAW_DATA'!B98 -> -6904 | C102: ='02_RAW_DATA'!C98 -> -8780 | D102: ='02_RAW_DATA'!D98 -> -9989
A103: Disposals of PP&E | B103: ='02_RAW_DATA'!B99 -> 52 | C103: ='02_RAW_DATA'!C99 -> 26 | D103: ='02_RAW_DATA'!D99 -> 68
A104: Investments in JV & associates | B104: ='02_RAW_DATA'!B100 -> -332 | C104: ='02_RAW_DATA'!C100 -> -396 | D104: ='02_RAW_DATA'!D100 -> -94
A105: Dividends received from JV, associates & other investments | B105: ='02_RAW_DATA'!B101 -> 176 | C105: ='02_RAW_DATA'!C101 -> 126 | D105: ='02_RAW_DATA'!D101 -> 105
A106: Disposal of UK Electricity System Operator | B106: ='02_RAW_DATA'!B102 -> 0 | C106: ='02_RAW_DATA'!C102 -> 577 | D106: ='02_RAW_DATA'!D102 -> 0
A107: Disposal of UK Gas Transmission interest | B107: ='02_RAW_DATA'!B103 -> 681 | C107: ='02_RAW_DATA'!C103 -> 686 | D107: ='02_RAW_DATA'!D103 -> 0
A108: Disposal of National Grid Renewables | B108: ='02_RAW_DATA'!B104 -> 0 | C108: ='02_RAW_DATA'!C104 -> 0 | D108: ='02_RAW_DATA'!D104 -> 1473
A109: Disposal of Grain LNG | B109: ='02_RAW_DATA'!B105 -> 0 | C109: ='02_RAW_DATA'!C105 -> 0 | D109: ='02_RAW_DATA'!D105 -> 1336
A110: Disposal of financial & other investments | B110: ='02_RAW_DATA'!B106 -> 102 | C110: ='02_RAW_DATA'!C106 -> 85 | D110: ='02_RAW_DATA'!D106 -> 67
A111: Acquisition of financial investments | B111: ='02_RAW_DATA'!B107 -> -81 | C111: ='02_RAW_DATA'!C107 -> -122 | D111: ='02_RAW_DATA'!D107 -> -67
...

Sheet 04_DRIVERS
A1: NATIONAL GRID PLC — FORECAST DRIVERS & ASSUMPTIONS
A3: Forecast Drivers | B3: FY2026A | C3: FY2027E | D3: FY2028E | E3: FY2029E | F3: FY2030E | G3: FY2031E | H3: Rationale/source
A5: CORE OPERATING DRIVERS
A6: Revenue growth | B6: =('03_HIST_FS'!D7) -> -0.037599304 | C6: 0.08 | D6: 0.07 | E6: 0.065 | F6: 0.06 | G6: 0.055 | H6: Model base-case assumption
A7: Operating margin | B7: ='03_HIST_FS'!D12 -> 0.30706168 | C7: 0.318 | D7: 0.32 | E7: 0.321 | F7: 0.322 | G7: 0.323 | H7: Model base-case assumption
A8: Effective tax rate | B8: ='03_HIST_FS'!D19 -> 0.22453372 | C8: 0.22 | D8: 0.22 | E8: 0.22 | F8: 0.22 | G8: 0.22 | H8: Normalised statutory tax assumption
A9: Capital Investment (£m) | B9: =11576 -> 11576 | C9: 13000 | D9: 13800 | E9: 14200 | F9: 14400 | G9: 14600 | H9: National Grid FY26 five-year financial framework
A10: Core cash capex (£m) | B10: ='03_HIST_FS'!D147 -> 10575 | C10: =C9*($B$10/$B$9) -> 11875.864 | D10: =D9*($B$10/$B$9) -> 12606.686 | E10: =E9*($B$10/$B$9) -> 12972.097 | F10: =F9*($B$10/$B$9) -> 13154.803 | G10: =G9*($B$10/$B$9) -> 13337.509 | H10: Derived from FY26 cash capex / capital investment ratio
A11: Capex intensity | B11: ='03_HIST_FS'!D148 -> 0.59789676 | H11: Model-calculated KPI
A12: Operating cash conversion | B12: ='03_HIST_FS'!D150 -> 1.4415393 | H12: Model-calculated KPI
A13: Group asset growth | B13: =10.9% -> 0.109 | C13: 0.1 | D13: 0.1 | E13: 0.1 | F13: 0.1 | G13: 0.1 | H13: Management guidance: ~10% asset CAGR
A14: Underlying EPS growth – sanity check | B14: 0.083 | C14: 0.14 | D14: 0.09 | E14: 0.09 | F14: 0.09 | G14: 0.09 | H14: FY27 guidance: 13–15%; five-year guidance: 8–10% CAGR
A16: PP&E additions / Capital investment | B16: =10425/'04_DRIVERS'!B9 -> 0.90057015 | C16: =90.1% -> 0.901 | D16: =90.1% -> 0.901 | E16: =90.1% -> 0.901 | F16: =90.1% -> 0.901 | G16: =90.1% -> 0.901
A17: Depreciation rate on opening PP&E | B17: =1989/74091 -> 0.026845366 | C17: =1989/74091 -> 0.026845366 | D17: =1989/74091 -> 0.026845366 | E17: =1989/74091 -> 0.026845366 | F17: =1989/74091 -> 0.026845366 | G17: =1989/74091 -> 0.026845366
A19: New borrowings / Capital investment | B19: =4172/B9 -> 0.36040083 | C19: 0.4 | D19: 0.4 | E19: 0.4 | F19: 0.4 | G19: 0.4
A20: Debt repayment % of opening debt | B20: =2961/47539 -> 0.062285702 | C20: 0.0625 | D20: 0.0625 | E20: 0.0625 | F20: 0.0625 | G20: 0.0625
A21: Effective interest rate | B21: =1705/((47539+46755)/2) -> 0.036163489 | C21: 0.038 | D21: 0.039 | E21: 0.04 | F21: 0.04 | G21: 0.04
A23: BALANCE SHEET DRIVERS
B24: FY27E–FY31E
A25: Inventory / Revenue | B25: 0.032
A26: Receivables / Revenue | B26: 0.215
A27: Payables / Revenue | B27: 0.285
A28: Other current assets / Revenue | B28: 0.15
A29: Intangible asset growth | B29: 0.05
A30: Other non-current asset growth | B30: 0.05
A31: Contract liability growth | B31: 0.07
A32: Deferred tax / PP&E | B32: 0.111
A33: Provisions & pensions growth | B33: 0.02
A34: Other liabilities / Revenue | B34: 0.123
A35: Dividend payout ratio | B35: 0.5
A37: Minimum cash balance (£m) | B37: 500
A38: Intangible amortisation rate | B38: 0.07

Sheet 05_INCOME_STATEMENT
A1: NATIONAL GRID PLC — INCOME STATEMENT FORECAST
A3: Income Statement (£m) | B3: FY2024A | C3: FY2025A | D3: FY2026A | E3: FY2027E | F3: FY2028E | G3: FY2029E | H3: FY2030E | I3: FY2031E
A5: Revenue | B5: ='03_HIST_FS'!B6 -> 19850 | C5: ='03_HIST_FS'!C6 -> 18378 | D5: ='03_HIST_FS'!D6 -> 17687 | E5: =D5*(1+'04_DRIVERS'!C6) -> 19101.96 | F5: =E5*(1+'04_DRIVERS'!D6) -> 20439.097 | G5: =F5*(1+'04_DRIVERS'!E6) -> 21767.639 | H5: =G5*(1+'04_DRIVERS'!F6) -> 23073.697 | I5: =H5*(1+'04_DRIVERS'!G6) -> 24342.75
A6: Revenue Growth | C6: =C5/B5-1 -> -0.074156171 | D6: =D5/C5-1 -> -0.037599304 | E6: ='04_DRIVERS'!C6 -> 0.08 | F6: ='04_DRIVERS'!D6 -> 0.07 | G6: ='04_DRIVERS'!E6 -> 0.065 | H6: ='04_DRIVERS'!F6 -> 0.06 | I6: ='04_DRIVERS'!G6 -> 0.055
A8: Operating profit | B8: ='03_HIST_FS'!B11 -> 4475 | C8: ='03_HIST_FS'!C11 -> 4934 | D8: ='03_HIST_FS'!D11 -> 5431 | E8: =E5*'04_DRIVERS'!C7 -> 6074.4233 | F8: =F5*'04_DRIVERS'!D7 -> 6540.5111 | G8: =G5*'04_DRIVERS'!E7 -> 6987.412 | H8: =H5*'04_DRIVERS'!F7 -> 7429.7304 | I8: =I5*'04_DRIVERS'!G7 -> 7862.7083
A9: Operating margin | B9: =B8/B5 -> 0.22544081 | C9: =C8/C5 -> 0.26847317 | D9: =D8/D5 -> 0.30706168 | E9: ='04_DRIVERS'!C7 -> 0.318 | F9: ='04_DRIVERS'!D7 -> 0.32 | G9: ='04_DRIVERS'!E7 -> 0.321 | H9: ='04_DRIVERS'!F7 -> 0.322 | I9: ='04_DRIVERS'!G7 -> 0.323
A11: Finance income | B11: ='03_HIST_FS'!B13 -> 248 | C11: ='03_HIST_FS'!C13 -> 450 | D11: ='03_HIST_FS'!D13 -> 380 | E11: =$D11 -> 380 | F11: =$D11 -> 380 | G11: =$D11 -> 380 | H11: =$D11 -> 380 | I11: =$D11 -> 380
A12: Finance costs | B12: ='03_HIST_FS'!B14 -> -1712 | C12: ='03_HIST_FS'!C14 -> -1807 | D12: ='03_HIST_FS'!D14 -> -1705 | E12: =-'09_DEBT'!C13 -> -1819.9684 | F12: =-'09_DEBT'!D13 -> -2134.2425 | G12: =-'09_DEBT'!E13 -> -2471.6146 | H12: =-'09_DEBT'!F13 -> -2754.5341 | I12: =-'09_DEBT'!G13 -> -3032.2927
A13: Share of JV & associates | B13: {='03_HIST_FS'!B15:D15} -> 37 | C13: 73 | D13: 76 | E13: =D13*1.03 -> 78.28 | F13: =E13*1.03 -> 80.6284 | G13: =F13*1.03 -> 83.047252 | H13: =G13*1.03 -> 85.53867 | I13: =H13*1.03 -> 88.10483
A15: Profit before tax | B15: ='03_HIST_FS'!B16 -> 3048 | C15: ='03_HIST_FS'!C16 -> 3650 | D15: ='03_HIST_FS'!D16 -> 4182 | E15: =E8+E11+E12+E13 -> 4712.7348 | F15: =F8+F11+F12+F13 -> 4866.897 | G15: =G8+G11+G12+G13 -> 4978.8446 | H15: =H8+H11+H12+H13 -> 5140.735 | I15: =I8+I11+I12+I13 -> 5298.5205
A16: Effective tax rate | B16: =-B17/B15 -> 0.2726378 | C16: =-C17/C15 -> 0.22493151 | D16: =-D17/D15 -> 0.22453372 | E16: ='04_DRIVERS'!C8 -> 0.22 | F16: ='04_DRIVERS'!D8 -> 0.22 | G16: ='04_DRIVERS'!E8 -> 0.22 | H16: ='04_DRIVERS'!F8 -> 0.22 | I16: ='04_DRIVERS'!G8 -> 0.22
A17: Tax expense | B17: ='03_HIST_FS'!B18 -> -831 | C17: ='03_HIST_FS'!C18 -> -821 | D17: ='03_HIST_FS'!D18 -> -939 | E17: =-E15*E16 -> -1036.8017 | F17: =-F15*F16 -> -1070.7173 | G17: =-G15*G16 -> -1095.3458 | H17: =-H15*H16 -> -1130.9617 | I17: =-I15*I16 -> -1165.6745
A19: Profit after tax | B19: ='03_HIST_FS'!B20 -> 2217 | C19: ='03_HIST_FS'!C20 -> 2829 | D19: ='03_HIST_FS'!D20 -> 3243 | E19: =E15+E17 -> 3675.9332 | F19: =F15+F17 -> 3796.1796 | G19: =G15+G17 -> 3883.4988 | H19: =H15+H17 -> 4009.7733 | I19: =I15+I17 -> 4132.846
A20: YoY PAT growth | C20: =C19/B19-1 -> 0.27604871 | D20: =D19/C19-1 -> 0.14634146 | E20: =E19/D19-1 -> 0.13349774 | F20: =F19/E19-1 -> 0.03271182 | G20: =G19/F19-1 -> 0.023001858 | H20: =H19/G19-1 -> 0.032515638 | I20: =I19/H19-1 -> 0.030693179

Sheet 06_BALANCE_SHEET
A1: NATIONAL GRID PLC — BALANCE SHEET FORECAST
A3: Balance Sheet (£m) | B3: FY2024A | C3: FY2025A | D3: FY2026A | E3: FY2027E | F3: FY2028E | G3: FY2029E | H3: FY2030E | I3: FY2031E
A5: ASSETS
A6: Goodwill | B6: ='03_HIST_FS'!B29 -> 9729 | C6: ='03_HIST_FS'!C29 -> 9532 | D6: ='03_HIST_FS'!D29 -> 9417 | E6: =$D6 -> 9417 | F6: =$D6 -> 9417 | G6: =$D6 -> 9417 | H6: =$D6 -> 9417 | I6: =$D6 -> 9417
A7: Other intangible assets | B7: ='03_HIST_FS'!B30 -> 3431 | C7: ='03_HIST_FS'!C30 -> 3564 | D7: ='03_HIST_FS'!D30 -> 3879 | E7: =D7*(1+'04_DRIVERS'!$B$29) -> 4072.95 | F7: =E7*(1+'04_DRIVERS'!$B$29) -> 4276.5975 | G7: =F7*(1+'04_DRIVERS'!$B$29) -> 4490.4274 | H7: =G7*(1+'04_DRIVERS'!$B$29) -> 4714.9487 | I7: =H7*(1+'04_DRIVERS'!$B$29) -> 4950.6962
A8: PP&E | B8: ='03_HIST_FS'!B31 -> 68907 | C8: ='03_HIST_FS'!C31 -> 74091 | D8: ='03_HIST_FS'!D31 -> 81520 | E8: ='08_CAPEX_PPE'!C9 -> 91044.566 | F8: ='08_CAPEX_PPE'!D9 -> 101034.24 | G8: ='08_CAPEX_PPE'!E9 -> 111116.14 | H8: ='08_CAPEX_PPE'!F9 -> 121107.59 | I8: ='08_CAPEX_PPE'!G9 -> 131011.01
A9: Other non-current assets | B9: =B10-B6-B7-B8 -> 5879 | C9: =C10-C6-C7-C8 -> 5223 | D9: =D10-D6-D7-D8 -> 5980 | E9: =D9*(1+'04_DRIVERS'!$B$30) -> 6279 | F9: =E9*(1+'04_DRIVERS'!$B$30) -> 6592.95 | G9: =F9*(1+'04_DRIVERS'!$B$30) -> 6922.5975 | H9: =G9*(1+'04_DRIVERS'!$B$30) -> 7268.7274 | I9: =H9*(1+'04_DRIVERS'!$B$30) -> 7632.1637
A10: Total non-current assets | B10: ='03_HIST_FS'!B37 -> 87946 | C10: ='03_HIST_FS'!C37 -> 92410 | D10: ='03_HIST_FS'!D37 -> 100796 | E10: =SUM(E6:E9) -> 110813.52 | F10: =SUM(F6:F9) -> 121320.79 | G10: =SUM(G6:G9) -> 131946.16 | H10: =SUM(H6:H9) -> 142508.26 | I10: =SUM(I6:I9) -> 153010.87
A12: Inventories | B12: ='03_HIST_FS'!B39 -> 828 | C12: ='03_HIST_FS'!C39 -> 557 | D12: ='03_HIST_FS'!D39 -> 559 | E12: ='05_INCOME_STATEMENT'!E5*'04_DRIVERS'!$B$25 -> 611.26272 | F12: ='05_INCOME_STATEMENT'!F5*'04_DRIVERS'!$B$25 -> 654.05111 | G12: ='05_INCOME_STATEMENT'!G5*'04_DRIVERS'!$B$25 -> 696.56443 | H12: ='05_INCOME_STATEMENT'!H5*'04_DRIVERS'!$B$25 -> 738.3583 | I12: ='05_INCOME_STATEMENT'!I5*'04_DRIVERS'!$B$25 -> 778.968
A13: Trade & other receivables | B13: ='03_HIST_FS'!B40 -> 3415 | C13: ='03_HIST_FS'!C40 -> 4092 | D13: ='03_HIST_FS'!D40 -> 3867 | E13: ='05_INCOME_STATEMENT'!E5*'04_DRIVERS'!$B$26 -> 4106.9214 | F13: ='05_INCOME_STATEMENT'!F5*'04_DRIVERS'!$B$26 -> 4394.4059 | G13: ='05_INCOME_STATEMENT'!G5*'04_DRIVERS'!$B$26 -> 4680.0423 | H13: ='05_INCOME_STATEMENT'!H5*'04_DRIVERS'!$B$26 -> 4960.8448 | I13: ='05_INCOME_STATEMENT'!I5*'04_DRIVERS'!$B$26 -> 5233.6913
A14: Cash & cash equivalents | B14: ='03_HIST_FS'!B44 -> 559 | C14: ='03_HIST_FS'!C44 -> 1178 | D14: ='03_HIST_FS'!D44 -> 375 | E14: ='07_CASH_FLOW'!E26 -> 500 | F14: ='07_CASH_FLOW'!F26 -> 500 | G14: ='07_CASH_FLOW'!G26 -> 500 | H14: ='07_CASH_FLOW'!H26 -> 500 | I14: ='07_CASH_FLOW'!I26 -> 500
A15: Other current assets | B15: =B16-B12-B13-B14 -> 5577 | C15: =C16-C12-C13-C14 -> 8505 | D15: =D16-D12-D13-D14 -> 2684 | E15: ='05_INCOME_STATEMENT'!E5*'04_DRIVERS'!$B$28 -> 2865.294 | F15: ='05_INCOME_STATEMENT'!F5*'04_DRIVERS'!$B$28 -> 3065.8646 | G15: ='05_INCOME_STATEMENT'!G5*'04_DRIVERS'!$B$28 -> 3265.1458 | H15: ='05_INCOME_STATEMENT'!H5*'04_DRIVERS'!$B$28 -> 3461.0545 | I15: ='05_INCOME_STATEMENT'!I5*'04_DRIVERS'!$B$28 -> 3651.4125
A16: Total current assets | B16: ='03_HIST_FS'!B46 -> 10379 | C16: ='03_HIST_FS'!C46 -> 14332 | D16: ='03_HIST_FS'!D46 -> 7485 | E16: =SUM(E12:E15) -> 8083.4781 | F16: =SUM(F12:F15) -> 8614.3216 | G16: =SUM(G12:G15) -> 9141.7525 | H16: =SUM(H12:H15) -> 9660.2576 | I16: =SUM(I12:I15) -> 10164.072
A18: TOTAL ASSETS | B18: =B10+B16 -> 98325 | C18: =C10+C16 -> 106742 | D18: =D10+D16 -> 108281 | E18: =E10+E16 -> 118896.99 | F18: =F10+F16 -> 129935.11 | G18: =G10+G16 -> 141087.92 | H18: =H10+H16 -> 152168.52 | I18: =I10+I16 -> 163174.94
A20: LIABILITIES
A21: Borrowings | B21: 47072 | C21: 47539 | D21: 46755 | E21: ='09_DEBT'!C9 -> 53640.431 | F21: ='09_DEBT'!D9 -> 60851.989 | G21: ='09_DEBT'!E9 -> 68111.847 | H21: ='09_DEBT'!F9 -> 75238.521 | I21: ='09_DEBT'!G9 -> 82236.157
A22: Trade & other payables | B22: 4076 | C22: 4472 | D22: 5049 | E22: ='05_INCOME_STATEMENT'!E5*'04_DRIVERS'!$B$27 -> 5444.0586 | F22: ='05_INCOME_STATEMENT'!F5*'04_DRIVERS'!$B$27 -> 5825.1427 | G22: ='05_INCOME_STATEMENT'!G5*'04_DRIVERS'!$B$27 -> 6203.777 | H22: ='05_INCOME_STATEMENT'!H5*'04_DRIVERS'!$B$27 -> 6576.0036 | I22: ='05_INCOME_STATEMENT'!I5*'04_DRIVERS'!$B$27 -> 6937.6838
A23: Contract liabilities | B23: 2246 | C23: 2514 | D23: 2809 | E23: =D23*(1+'04_DRIVERS'!$B$31) -> 3005.63 | F23: =E23*(1+'04_DRIVERS'!$B$31) -> 3216.0241 | G23: =F23*(1+'04_DRIVERS'!$B$31) -> 3441.1458 | H23: =G23*(1+'04_DRIVERS'!$B$31) -> 3682.026 | I23: =H23*(1+'04_DRIVERS'!$B$31) -> 3939.7678
A24: Deferred tax liabilities | B24: 7519 | C24: 8038 | D24: 9040 | E24: =E8*'04_DRIVERS'!$B$32 -> 10105.947 | F24: =F8*'04_DRIVERS'!$B$32 -> 11214.801 | G24: =G8*'04_DRIVERS'!$B$32 -> 12333.892 | H24: =H8*'04_DRIVERS'!$B$32 -> 13442.942 | I24: =I8*'04_DRIVERS'!$B$32 -> 14542.222
A25: Provisions & pensions | B25: 3702 | C25: 3622 | D25: 3121 | E25: =D25*(1+'04_DRIVERS'!$B$33) -> 3183.42 | F25: =E25*(1+'04_DRIVERS'!$B$33) -> 3247.0884 | G25: =F25*(1+'04_DRIVERS'!$B$33) -> 3312.0302 | H25: =G25*(1+'04_DRIVERS'!$B$33) -> 3378.2708 | I25: =H25*(1+'04_DRIVERS'!$B$33) -> 3445.8362
A26: Derivatives & other liabilities | B26: 3818 | C26: 2731 | D26: 2177 | E26: ='05_INCOME_STATEMENT'!E5*'04_DRIVERS'!$B$34 -> 2349.5411 | F26: ='05_INCOME_STATEMENT'!F5*'04_DRIVERS'!$B$34 -> 2514.009 | G26: ='05_INCOME_STATEMENT'!G5*'04_DRIVERS'!$B$34 -> 2677.4195 | H26: ='05_INCOME_STATEMENT'!H5*'04_DRIVERS'!$B$34 -> 2838.0647 | I26: ='05_INCOME_STATEMENT'!I5*'04_DRIVERS'!$B$34 -> 2994.1583
A27: TOTAL LIABILITIES | B27: =SUM(B20:B26) -> 68433 | C27: =SUM(C20:C26) -> 68916 | D27: =SUM(D20:D26) -> 68951 | E27: =SUM(E21:E26) -> 77729.027 | F27: =SUM(F21:F26) -> 86869.054 | G27: =SUM(G21:G26) -> 96080.111 | H27: =SUM(H21:H26) -> 105155.83 | I27: =SUM(I21:I26) -> 114095.83
A29: EQUITY
A30: Opening equity | C30: =B34 -> 29892 | D30: =C34 -> 37826 | E30: =D34 -> 39330 | F30: =E34 -> 41167.967 | G30: =F34 -> 43066.056 | H30: =G34 -> 45007.806 | I30: =H34 -> 47012.692
A31: Profit after tax | C31: ='05_INCOME_STATEMENT'!C19 -> 2829 | D31: ='05_INCOME_STATEMENT'!D19 -> 3243 | E31: ='05_INCOME_STATEMENT'!E19 -> 3675.9332 | F31: ='05_INCOME_STATEMENT'!F19 -> 3796.1796 | G31: ='05_INCOME_STATEMENT'!G19 -> 3883.4988 | H31: ='05_INCOME_STATEMENT'!H19 -> 4009.7733 | I31: ='05_INCOME_STATEMENT'!I19 -> 4132.846
A32: Dividends | C32: =-1529 -> -1529 | D32: =-1623 -> -1623 | E32: =-E31*'04_DRIVERS'!$B$35 -> -1837.9666 | F32: =-F31*'04_DRIVERS'!$B$35 -> -1898.0898 | G32: =-G31*'04_DRIVERS'!$B$35 -> -1941.7494 | H32: =-H31*'04_DRIVERS'!$B$35 -> -2004.8866 | I32: =-I31*'04_DRIVERS'!$B$35 -> -2066.423
A33: Other equity movements | C33: =C34-C30-C31-C32 -> 6634 | D33: =D34-D30-D31-D32 -> -116 | E33: =0 -> 0 | F33: =0 -> 0 | G33: =0 -> 0 | H33: =0 -> 0 | I33: =0 -> 0
A34: Closing equity | B34: =29892 -> 29892 | C34: =37826 -> 37826 | D34: 39330 | E34: =SUM(E30:E33) -> 41167.967 | F34: =SUM(F30:F33) -> 43066.056 | G34: =SUM(G30:G33) -> 45007.806 | H34: =SUM(H30:H33) -> 47012.692 | I34: =SUM(I30:I33) -> 49079.115
A36: TOTAL LIABILITIES & EQUITY | B36: =B27+B34 -> 98325 | C36: =C27+C34 -> 106742 | D36: =D27+D34 -> 108281 | E36: =E27+E34 -> 118896.99 | F36: =F27+F34 -> 129935.11 | G36: =G27+G34 -> 141087.92 | H36: =H27+H34 -> 152168.52 | I36: =I27+I34 -> 163174.94
A38: BALANCE CHECK | B38: =B18-B36 -> 0 | C38: =C18-C36 -> 0 | D38: =D18-D36 -> 0 | E38: =E18-E36 -> 0 | F38: =F18-F36 -> 0 | G38: =G18-G36 -> 0 | H38: =H18-H36 -> 0 | I38: =I18-I36 -> 0

Sheet 07_CASH_FLOW
A1: NATIONAL GRID PLC — CASH FLOW FORECAST
A3: Cash Flow Statement (£m) | B3: FY2024A | C3: FY2025A | D3: FY2026A | E3: FY2027E | F3: FY2028E | G3: FY2029E | H3: FY2030E | I3: FY2031E
A4: Operating profit | B4: 4475 | C4: 4934 | D4: 5431 | E4: ='05_INCOME_STATEMENT'!E8 -> 6074.4233 | F4: ='05_INCOME_STATEMENT'!F8 -> 6540.5111 | G4: ='05_INCOME_STATEMENT'!G8 -> 6987.412 | H4: ='05_INCOME_STATEMENT'!H8 -> 7429.7304 | I4: ='05_INCOME_STATEMENT'!I8 -> 7862.7083
A5: Depreciation & amortisation | B5: 2061 | C5: 2175 | D5: 2247 | E5: ='08_CAPEX_PPE'!C7+'06_BALANCE_SHEET'!D7*'04_DRIVERS'!$B$38 -> 2459.9642 | F5: ='08_CAPEX_PPE'!D7+'06_BALANCE_SHEET'!E7*'04_DRIVERS'!$B$38 -> 2729.2312 | G5: ='08_CAPEX_PPE'!E7+'06_BALANCE_SHEET'!F7*'04_DRIVERS'!$B$38 -> 3011.663 | H5: ='08_CAPEX_PPE'!F7+'06_BALANCE_SHEET'!G7*'04_DRIVERS'!$B$38 -> 3297.2833 | I5: ='08_CAPEX_PPE'!G7+'06_BALANCE_SHEET'!H7*'04_DRIVERS'!$B$38 -> 3581.2239
A6: Working capital movement | B6: -49 | C6: 104 | D6: 759 | E6: =-('06_BALANCE_SHEET'!E12-'06_BALANCE_SHEET'!D12)-('06_BALANCE_SHEET'!E13-'06_BALANCE_SHEET'!D13)+('06_BALANCE_SHEET'!E22-'06_BALANCE_SHEET'!D22)+('06_BALANCE_SHEET'!E23-'06_BALANCE_SHEET'!D23) -> 299.50448 | F6: =-('06_BALANCE_SHEET'!F12-'06_BALANCE_SHEET'!E12)-('06_BALANCE_SHEET'!F13-'06_BALANCE_SHEET'!E13)+('06_BALANCE_SHEET'!F22-'06_BALANCE_SHEET'!E22)+('06_BALANCE_SHEET'!F23-'06_BALANCE_SHEET'!E23) -> 261.20531 | G6: =-('06_BALANCE_SHEET'!G12-'06_BALANCE_SHEET'!F12)-('06_BALANCE_SHEET'!G13-'06_BALANCE_SHEET'!F13)+('06_BALANCE_SHEET'!G22-'06_BALANCE_SHEET'!F22)+('06_BALANCE_SHEET'!G23-'06_BALANCE_SHEET'!F23) -> 275.60626 | H6: =-('06_BALANCE_SHEET'!H12-'06_BALANCE_SHEET'!G12)-('06_BALANCE_SHEET'!H13-'06_BALANCE_SHEET'!G13)+('06_BALANCE_SHEET'!H22-'06_BALANCE_SHEET'!G22)+('06_BALANCE_SHEET'!H23-'06_BALANCE_SHEET'!G23) -> 290.51042 | I6: =-('06_BALANCE_SHEET'!I12-'06_BALANCE_SHEET'!H12)-('06_BALANCE_SHEET'!I13-'06_BALANCE_SHEET'!H13)+('06_BALANCE_SHEET'!I22-'06_BALANCE_SHEET'!H22)+('06_BALANCE_SHEET'!I23-'06_BALANCE_SHEET'!H23) -> 305.96585
A7: Provisions / pensions movement | B7: -123 | C7: -80 | D7: -158 | E7: ='06_BALANCE_SHEET'!E25-'06_BALANCE_SHEET'!D25 -> 62.42 | F7: ='06_BALANCE_SHEET'!F25-'06_BALANCE_SHEET'!E25 -> 63.6684 | G7: ='06_BALANCE_SHEET'!G25-'06_BALANCE_SHEET'!F25 -> 64.941768 | H7: ='06_BALANCE_SHEET'!H25-'06_BALANCE_SHEET'!G25 -> 66.240603 | I7: ='06_BALANCE_SHEET'!I25-'06_BALANCE_SHEET'!H25 -> 67.565415
A8: Other operating adjustments | B8: 917 | C8: -142 | D8: -418 | E8: ='05_INCOME_STATEMENT'!E11+'05_INCOME_STATEMENT'!E13+('06_BALANCE_SHEET'!E24-'06_BALANCE_SHEET'!D24)+('06_BALANCE_SHEET'!E26-'06_BALANCE_SHEET'!D26) -> 1696.7679 | F8: ='05_INCOME_STATEMENT'!F11+'05_INCOME_STATEMENT'!F13+('06_BALANCE_SHEET'!F24-'06_BALANCE_SHEET'!E24)+('06_BALANCE_SHEET'!F26-'06_BALANCE_SHEET'!E26) -> 1733.9502 | G8: ='05_INCOME_STATEMENT'!G11+'05_INCOME_STATEMENT'!G13+('06_BALANCE_SHEET'!G24-'06_BALANCE_SHEET'!F24)+('06_BALANCE_SHEET'!G26-'06_BALANCE_SHEET'!F26) -> 1745.5486 | H8: ='05_INCOME_STATEMENT'!H11+'05_INCOME_STATEMENT'!H13+('06_BALANCE_SHEET'!H24-'06_BALANCE_SHEET'!G24)+('06_BALANCE_SHEET'!H26-'06_BALANCE_SHEET'!G26) -> 1735.2344 | I8: ='05_INCOME_STATEMENT'!I11+'05_INCOME_STATEMENT'!I13+('06_BALANCE_SHEET'!I24-'06_BALANCE_SHEET'!H24)+('06_BALANCE_SHEET'!I26-'06_BALANCE_SHEET'!H26) -> 1723.4783
A9: Cash generated from operations | B9: 7281 | C9: 6991 | D9: 7861 | E9: =SUM(E4:E8) -> 10593.08 | F9: =SUM(F4:F8) -> 11328.566 | G9: =SUM(G4:G8) -> 12085.172 | H9: =SUM(H4:H8) -> 12818.999 | I9: =SUM(I4:I8) -> 13540.942
A10: Tax paid | B10: -342 | C10: -183 | D10: -32 | E10: ='05_INCOME_STATEMENT'!E17 -> -1036.8017 | F10: ='05_INCOME_STATEMENT'!F17 -> -1070.7173 | G10: ='05_INCOME_STATEMENT'!G17 -> -1095.3458 | H10: ='05_INCOME_STATEMENT'!H17 -> -1130.9617 | I10: ='05_INCOME_STATEMENT'!I17 -> -1165.6745
A11: NET OPERATING CASH FLOW | B11: 6939 | C11: 6808 | D11: 7829 | E11: =E9+E10 -> 9556.2782 | F11: =F9+F10 -> 10257.849 | G11: =G9+G10 -> 10989.826 | H11: =H9+H10 -> 11688.037 | I11: =I9+I10 -> 12375.267
A12: Purchases of intangible assets | B12: -549 | C12: -526 | D12: -586 | E12: =-(('06_BALANCE_SHEET'!E7-'06_BALANCE_SHEET'!D7)+('06_BALANCE_SHEET'!D7*'04_DRIVERS'!$B$38)) -> -465.48 | F12: =-(('06_BALANCE_SHEET'!F7-'06_BALANCE_SHEET'!E7)+('06_BALANCE_SHEET'!E7*'04_DRIVERS'!$B$38)) -> -488.754 | G12: =-(('06_BALANCE_SHEET'!G7-'06_BALANCE_SHEET'!F7)+('06_BALANCE_SHEET'!F7*'04_DRIVERS'!$B$38)) -> -513.1917 | H12: =-(('06_BALANCE_SHEET'!H7-'06_BALANCE_SHEET'!G7)+('06_BALANCE_SHEET'!G7*'04_DRIVERS'!$B$38)) -> -538.85129 | I12: =-(('06_BALANCE_SHEET'!I7-'06_BALANCE_SHEET'!H7)+('06_BALANCE_SHEET'!H7*'04_DRIVERS'!$B$38)) -> -565.79385
A13: Purchases of PP&E | B13: -6904 | C13: -8780 | D13: -9989 | E13: =-'08_CAPEX_PPE'!C6 -> -11713 | F13: =-'08_CAPEX_PPE'!D6 -> -12433.8 | G13: =-'08_CAPEX_PPE'!E6 -> -12794.2 | H13: =-'08_CAPEX_PPE'!F6 -> -12974.4 | I13: =-'08_CAPEX_PPE'!G6 -> -13154.6
A14: Other investing cash flows | B14: -148 | C14: -1287 | D14: 6418 | E14: =-('06_BALANCE_SHEET'!E9-'06_BALANCE_SHEET'!D9)-('06_BALANCE_SHEET'!E15-'06_BALANCE_SHEET'!D15) -> -480.294 | F14: =-('06_BALANCE_SHEET'!F9-'06_BALANCE_SHEET'!E9)-('06_BALANCE_SHEET'!F15-'06_BALANCE_SHEET'!E15) -> -514.52058 | G14: =-('06_BALANCE_SHEET'!G9-'06_BALANCE_SHEET'!F9)-('06_BALANCE_SHEET'!G15-'06_BALANCE_SHEET'!F15) -> -528.9287 | H14: =-('06_BALANCE_SHEET'!H9-'06_BALANCE_SHEET'!G9)-('06_BALANCE_SHEET'!H15-'06_BALANCE_SHEET'!G15) -> -542.03862 | I14: =-('06_BALANCE_SHEET'!I9-'06_BALANCE_SHEET'!H9)-('06_BALANCE_SHEET'!I15-'06_BALANCE_SHEET'!H15) -> -553.79437
A15: NET INVESTING CASH FLOW | B15: -7601 | C15: -10593 | D15: -4157 | E15: =SUM(E12:E14) -> -12658.774 | F15: =SUM(F12:F14) -> -13437.075 | G15: =SUM(G12:G14) -> -13836.32 | H15: =SUM(H12:H14) -> -14055.29 | I15: =SUM(I12:I14) -> -14274.188
A16: New borrowings — base | B16: 5563 | C16: 3237 | D16: 4172 | E16: ='09_DEBT'!C6 -> 5200 | F16: ='09_DEBT'!D6 -> 5520 | G16: ='09_DEBT'!E6 -> 5680 | H16: ='09_DEBT'!F6 -> 5760 | I16: ='09_DEBT'!G6 -> 5840
A17: Additional liquidity funding | B17: - | C17: - | D17: - | E17: =MAX(0,'04_DRIVERS'!$B$37-(E23+E11+E15+E16+E18+E19+E20+E21+E25)) -> 4607.6183 | F17: =MAX(0,'04_DRIVERS'!$B$37-(F23+F11+F15+F16+F18+F19+F20+F21+F25)) -> 5044.085 | G17: =MAX(0,'04_DRIVERS'!$B$37-(G23+G11+G15+G16+G18+G19+G20+G21+G25)) -> 5383.1079 | H17: =MAX(0,'04_DRIVERS'!$B$37-(H23+H11+H15+H16+H18+H19+H20+H21+H25)) -> 5623.6636 | I17: =MAX(0,'04_DRIVERS'!$B$37-(I23+I11+I15+I16+I18+I19+I20+I21+I25)) -> 5860.0442
A18: Debt repayments | B18: -1701 | C18: -2861 | D18: -2961 | E18: =-'09_DEBT'!C7 -> -2922.1875 | F18: =-'09_DEBT'!D7 -> -3352.5269 | G18: =-'09_DEBT'!E7 -> -3803.2493 | H18: =-'09_DEBT'!F7 -> -4256.9905 | I18: =-'09_DEBT'!G7 -> -4702.4075
A19: Interest paid | B19: -1627 | C19: -1920 | D19: -1932 | E19: =-'09_DEBT'!C13 -> -1819.9684 | F19: =-'09_DEBT'!D13 -> -2134.2425 | G19: =-'09_DEBT'!E13 -> -2471.6146 | H19: =-'09_DEBT'!F13 -> -2754.5341 | I19: =-'09_DEBT'!G13 -> -3032.2927
A20: Dividends paid | B20: -1718 | C20: -1529 | D20: -1623 | E20: ='06_BALANCE_SHEET'!E32 -> -1837.9666 | F20: ='06_BALANCE_SHEET'!F32 -> -1898.0898 | G20: ='06_BALANCE_SHEET'!G32 -> -1941.7494 | H20: ='06_BALANCE_SHEET'!H32 -> -2004.8866 | I20: ='06_BALANCE_SHEET'!I32 -> -2066.423
A21: Other financing cash flows | B21: 470 | C21: 7601 | D21: -2276 | E21: =0 -> 0 | F21: =0 -> 0 | G21: =0 -> 0 | H21: =0 -> 0 | I21: =0 -> 0
A22: NET FINANCING CASH FLOW | B22: 987 | C22: 4528 | D22: -4620 | E22: =SUM(E16:E21) -> 3227.4958 | F22: =SUM(F16:F21) -> 3179.2257 | G22: =SUM(G16:G21) -> 2846.4946 | H22: =SUM(H16:H21) -> 2367.2524 | I22: =SUM(I16:I21) -> 1898.921
A23: Opening cash | B23: 163 | C23: 559 | D23: 1178 | E23: =D26 -> 375 | F23: =E26 -> 500 | G23: =F26 -> 500 | H23: =G26 -> 500 | I23: =H26 -> 500
A24: Net change in cash | B24: 427 | C24: 765 | D24: -948 | E24: =E11+E15+E22 -> 125 | F24: =F11+F15+F22 -> 0 | G24: =G11+G15+G22 -> 0 | H24: =H11+H15+H22 -> 0 | I24: =I11+I15+I22 -> 0
A25: FX / held-for-sale / other | B25: -31 | C25: -146 | D25: 145 | E25: =0 -> 0 | F25: =0 -> 0 | G25: =0 -> 0 | H25: =0 -> 0 | I25: =0 -> 0
A26: ENDING CASH | B26: 559 | C26: 1178 | D26: 375 | E26: =E23+E24+E25 -> 500 | F26: =F23+F24+F25 -> 500 | G26: =G23+G24+G25 -> 500 | H26: =H23+H24+H25 -> 500 | I26: =I23+I24+I25 -> 500

Sheet 08_CAPEX_PPE
A1: NATIONAL GRID PLC — CAPEX & PP&E SCHEDULE
A3: PP&E Schedule (£m) | B3: FY2026A | C3: FY2027E | D3: FY2028E | E3: FY2029E | F3: FY2030E | G3: FY2031E
A5: Opening PP&E | B5: 74091 | C5: =B9 -> 81520 | D5: =C9 -> 91044.566 | E5: =D9 -> 101034.24 | F5: =E9 -> 111116.14 | G5: =F9 -> 121107.59
A6: PP&E additions | B6: 10425 | C6: ='04_DRIVERS'!C9*'04_DRIVERS'!C16 -> 11713 | D6: ='04_DRIVERS'!D9*'04_DRIVERS'!D16 -> 12433.8 | E6: ='04_DRIVERS'!E9*'04_DRIVERS'!E16 -> 12794.2 | F6: ='04_DRIVERS'!F9*'04_DRIVERS'!F16 -> 12974.4 | G6: ='04_DRIVERS'!G9*'04_DRIVERS'!G16 -> 13154.6
A7: Depreciation | B7: 1989 | C7: =C5*'04_DRIVERS'!C17 -> 2188.4342 | D7: =D5*'04_DRIVERS'!D17 -> 2444.1247 | E7: =E5*'04_DRIVERS'!E17 -> 2712.3012 | F7: =F5*'04_DRIVERS'!F17 -> 2982.9534 | G7: =G5*'04_DRIVERS'!G17 -> 3251.1775
A8: FX / disposals / other | B8: =B9-B5-B6+B7 -> -1007 | C8: 0 | D8: 0 | E8: 0 | F8: 0 | G8: 0
A9: Closing PP&E | B9: 81520 | C9: =C5+C6-C7+C8 -> 91044.566 | D9: =D5+D6-D7+D8 -> 101034.24 | E9: =E5+E6-E7+E8 -> 111116.14 | F9: =F5+F6-F7+F8 -> 121107.59 | G9: =G5+G6-G7+G8 -> 131011.01
A11: PP&E additions / Capital investment | B11: =B6/'04_DRIVERS'!B9 -> 0.90057015 | C11: =C6/'04_DRIVERS'!C9 -> 0.901 | D11: =D6/'04_DRIVERS'!D9 -> 0.901 | E11: =E6/'04_DRIVERS'!E9 -> 0.901 | F11: =F6/'04_DRIVERS'!F9 -> 0.901 | G11: =G6/'04_DRIVERS'!G9 -> 0.901
A12: Depreciation rate | B12: =B7/B5 -> 0.026845366 | C12: =C7/C5 -> 0.026845366 | D12: =D7/D5 -> 0.026845366 | E12: =E7/E5 -> 0.026845366 | F12: =F7/F5 -> 0.026845366 | G12: =G7/G5 -> 0.026845366
A13: Implied PP&E growth | B13: =B9/B5-1 -> 0.10026859 | C13: =C9/C5-1 -> 0.11683717 | D13: =D9/D5-1 -> 0.10972292 | E13: =E9/E5-1 -> 0.099786951 | F13: =F9/F5-1 -> 0.089918949 | G13: =G9/G5-1 -> 0.081773759
A14: Group asset growth — guidance check | B14: ='04_DRIVERS'!B13 -> 0.109 | C14: ='04_DRIVERS'!C13 -> 0.1 | D14: ='04_DRIVERS'!D13 -> 0.1 | E14: ='04_DRIVERS'!E13 -> 0.1 | F14: ='04_DRIVERS'!F13 -> 0.1 | G14: ='04_DRIVERS'!G13 -> 0.1

Sheet 09_DEBT
A1: NATIONAL GRID PLC — DEBT & INTEREST SCHEDULE
A3: Debt Schedule (£m) | B3: FY2026A | C3: FY2027E | D3: FY2028E | E3: FY2029E | F3: FY2030E | G3: FY2031E
A5: Opening gross debt | B5: 47539 | C5: =B9 -> 46755 | D5: =C9 -> 53640.431 | E5: =D9 -> 60851.989 | F5: =E9 -> 68111.847 | G5: =F9 -> 75238.521
A6: Base New borrowings | B6: 4172 | C6: ='04_DRIVERS'!C9*'04_DRIVERS'!C19 -> 5200 | D6: ='04_DRIVERS'!D9*'04_DRIVERS'!D19 -> 5520 | E6: ='04_DRIVERS'!E9*'04_DRIVERS'!E19 -> 5680 | F6: ='04_DRIVERS'!F9*'04_DRIVERS'!F19 -> 5760 | G6: ='04_DRIVERS'!G9*'04_DRIVERS'!G19 -> 5840
A7: Debt repayments | B7: 2961 | C7: =C5*'04_DRIVERS'!C20 -> 2922.1875 | D7: =D5*'04_DRIVERS'!D20 -> 3352.5269 | E7: =E5*'04_DRIVERS'!E20 -> 3803.2493 | F7: =F5*'04_DRIVERS'!F20 -> 4256.9905 | G7: =G5*'04_DRIVERS'!G20 -> 4702.4075
A8: FX / fair value / other movements | B8: =B9-B5-B6+B7 -> -1995 | C8: 0 | D8: 0 | E8: 0 | F8: 0 | G8: 0
A9: Closing gross debt | B9: 46755 | C9: =C5+C6+C14-C7+C8 -> 53640.431 | D9: =D5+D6+D14-D7+D8 -> 60851.989 | E9: =E5+E6+E14-E7+E8 -> 68111.847 | F9: =F5+F6+F14-F7+F8 -> 75238.521 | G9: =G5+G6+G14-G7+G8 -> 82236.157
A11: Average gross debt | B11: =(B5+B9)/2 -> 47147 | C11: =(C5+(C5+C6-C7+C8))/2 -> 47893.906 | D11: =(D5+(D5+D6-D7+D8))/2 -> 54724.167 | E11: =(E5+(E5+E6-E7+E8))/2 -> 61790.364 | F11: =(F5+(F5+F6-F7+F8))/2 -> 68863.352 | G11: =(G5+(G5+G6-G7+G8))/2 -> 75807.317
A12: Effective interest rate | B12: =1705/B11 -> 0.036163489 | C12: ='04_DRIVERS'!C21 -> 0.038 | D12: ='04_DRIVERS'!D21 -> 0.039 | E12: ='04_DRIVERS'!E21 -> 0.04 | F12: ='04_DRIVERS'!F21 -> 0.04 | G12: ='04_DRIVERS'!G21 -> 0.04
A13: Finance cost | B13: 1705 | C13: =C11*C12 -> 1819.9684 | D13: =D11*D12 -> 2134.2425 | E13: =E11*E12 -> 2471.6146 | F13: =F11*F12 -> 2754.5341 | G13: =G11*G12 -> 3032.2927
A14: Additional liquidity funding (year-end) | B14: 0 | C14: ='07_CASH_FLOW'!E17 -> 4607.6183 | D14: ='07_CASH_FLOW'!F17 -> 5044.085 | E14: ='07_CASH_FLOW'!G17 -> 5383.1079 | F14: ='07_CASH_FLOW'!H17 -> 5623.6636 | G14: ='07_CASH_FLOW'!I17 -> 5860.0442
A15: New borrowings / Capital investment | B15: =B6/'04_DRIVERS'!B9 -> 0.36040083 | C15: =C6/'04_DRIVERS'!C9 -> 0.4 | D15: =D6/'04_DRIVERS'!D9 -> 0.4 | E15: =E6/'04_DRIVERS'!E9 -> 0.4 | F15: =F6/'04_DRIVERS'!F9 -> 0.4 | G15: =G6/'04_DRIVERS'!G9 -> 0.4
A16: Debt repayment % of opening debt | B16: =B7/B5 -> 0.062285702 | C16: =C7/C5 -> 0.0625 | D16: =D7/D5 -> 0.0625 | E16: =E7/E5 -> 0.0625 | F16: =F7/F5 -> 0.0625 | G16: =G7/G5 -> 0.0625
A17: Gross debt growth | B17: =B9/B5-1 -> -0.016491723 | C17: =C9/C5-1 -> 0.14726619 | D17: =D9/D5-1 -> 0.13444258 | E17: =E9/E5-1 -> 0.11930356 | F17: =F9/F5-1 -> 0.10463192 | G17: =G9/G5-1 -> 0.093006037

Sheet 10_FPA_VARIANCE
A1: NATIONAL GRID PLC — FP&A VARIANCE ANALYSIS
A2: FY2027 Budget is an illustrative management budget created for this portfolio case study and is not published National Grid guidance.
A4: Metric | B4: FY2026A Actual | C4: FY2027 Budget | D4: FY2027 Latest Forecast | E4: Variance vs Budget | F4: Variance % | G4: YoY vs Actual | H4: F/A | I4: Management Commentary
A5: Revenue (£m) | B5: ='05_INCOME_STATEMENT'!D5 -> 17687 | C5: 19500 | D5: ='05_INCOME_STATEMENT'!E5 -> 19101.96 | E5: =D5-C5 -> -398.04 | F5: =IFERROR(D5/C5-1,0) -> -0.020412308 | G5: =IFERROR(D5/B5-1,0) -> 0.08 | H5: =IF(E5>=0,"F","A") -> A | I5: =IF(E5>=0,"Revenue forecast is £"&TEXT(E5,"#,##0")&"m above budget.","Revenue forecast is £"&TEXT(ABS(E5),"#,##0")&"m below budget; investigate timing, volumes and regulated revenue assumptions.") -> Revenue forecast is £398m below budget; investigate timing, volumes and regulated revenue assumptions.
A6: Operating profit (£m) | B6: ='05_INCOME_STATEMENT'!D8 -> 5431 | C6: 6143 | D6: ='05_INCOME_STATEMENT'!E8 -> 6074.4233 | E6: =D6-C6 -> -68.57672 | F6: =IFERROR(D6/C6-1,0) -> -0.011163392 | G6: =IFERROR(D6/B6-1,0) -> 0.11847234 | H6: =IF(E6>=0,"F","A") -> A | I6: =IF(E6>=0,"Operating profit is £"&TEXT(E6,"#,##0")&"m above budget.","Operating profit is £"&TEXT(ABS(E6),"#,##0")&"m below budget; assess revenue performance versus margin protection.") -> Operating profit is £69m below budget; assess revenue performance versus margin protection.
A7: Operating margin | B7: ='05_INCOME_STATEMENT'!D9 -> 0.30706168 | C7: 0.315 | D7: ='05_INCOME_STATEMENT'!E9 -> 0.318 | E7: =D7-C7 -> 0.003 | F7: ="" | G7: =D7-B7 -> 0.010938316 | H7: =IF(E7>=0,"F","A") -> F | I7: =IF(E7>=0,"Operating margin is "&TEXT(E7*100,"0.0")&"pp above budget, indicating stronger operating efficiency.","Operating margin is "&TEXT(ABS(E7)*100,"0.0")&"pp below budget; review operating cost control.") -> Operating margin is 0.3pp above budget, indicating stronger operating efficiency.
A8: Capital investment (£m) | B8: ='04_DRIVERS'!B9 -> 11576 | C8: 12800 | D8: ='04_DRIVERS'!C9 -> 13000 | E8: =D8-C8 -> 200 | F8: =IFERROR(D8/C8-1,0) -> 0.015625 | G8: =IFERROR(D8/B8-1,0) -> 0.12301313 | H8: =IF(E8<=0,"F","A") -> A | I8: =IF(E8<=0,"Capital investment is £"&TEXT(ABS(E8),"#,##0")&"m below budget.","Capital investment is £"&TEXT(E8,"#,##0")&"m above budget; review project timing, delivery and funding requirements.") -> Capital investment is £200m above budget; review project timing, delivery and funding requirements.
A9: Net operating cash flow (£m) | B9: ='07_CASH_FLOW'!D11 -> 7829 | C9: 9300 | D9: ='07_CASH_FLOW'!E11 -> 9556.2782 | E9: =D9-C9 -> 256.2782 | F9: =IFERROR(D9/C9-1,0) -> 0.027556796 | G9: =IFERROR(D9/B9-1,0) -> 0.22062565 | H9: =IF(E9>=0,"F","A") -> F | I9: =IF(E9>=0,"Operating cash flow is £"&TEXT(E9,"#,##0")&"m above budget.","Operating cash flow is £"&TEXT(ABS(E9),"#,##0")&"m below budget; review working capital and cash conversion.") -> Operating cash flow is £256m above budget.
A10: Finance cost (£m) | B10: ='09_DEBT'!B13 -> 1705 | C10: 1800 | D10: ='09_DEBT'!C13 -> 1819.9684 | E10: =D10-C10 -> 19.968437 | F10: =IFERROR(D10/C10-1,0) -> 0.011093576 | G10: =IFERROR(D10/B10-1,0) -> 0.067430169 | H10: =IF(E10<=0,"F","A") -> A | I10: =IF(E10<=0,"Finance cost is £"&TEXT(ABS(E10),"#,##0")&"m below budget.","Finance cost is £"&TEXT(E10,"#,##0")&"m above budget due to higher funding requirements and debt levels.") -> Finance cost is £20m above budget due to higher funding requirements and debt levels.
A11: Profit after tax (£m) | B11: ='05_INCOME_STATEMENT'!D19 -> 3243 | C11: 3650 | D11: ='05_INCOME_STATEMENT'!E19 -> 3675.9332 | E11: =D11-C11 -> 25.933177 | F11: =IFERROR(D11/C11-1,0) -> 0.00710498 | G11: =IFERROR(D11/B11-1,0) -> 0.13349774 | H11: =IF(E11>=0,"F","A") -> F | I11: =IF(E11>=0,"Profit after tax is £"&TEXT(E11,"#,##0")&"m above budget.","Profit after tax is £"&TEXT(ABS(E11),"#,##0")&"m below budget; review operating performance and financing costs.") -> Profit after tax is £26m above budget.
A12: Closing gross debt (£m) | B12: ='09_DEBT'!B9 -> 46755 | C12: 52500 | D12: ='09_DEBT'!C9 -> 53640.431 | E12: =D12-C12 -> 1140.4308 | F12: =IFERROR(D12/C12-1,0) -> 0.021722492 | G12: =IFERROR(D12/B12-1,0) -> 0.14726619 | H12: =IF(E12<=0,"F","A") -> A | I12: =IF(E12<=0,"Closing debt is £"&TEXT(ABS(E12),"#,##0")&"m below budget.","Closing debt is £"&TEXT(E12,"#,##0")&"m above budget; monitor leverage and financing capacity.") -> Closing debt is £1,140m above budget; monitor leverage and financing capacity.
A13: Additional liquidity funding (£m) | B13: ='09_DEBT'!B14 -> 0 | C13: 4000 | D13: ='09_DEBT'!C14 -> 4607.6183 | E13: =D13-C13 -> 607.61833 | F13: =IFERROR(D13/C13-1,0) -> 0.15190458 | G13: ="" | H13: =IF(E13<=0,"F","A") -> A | I13: =IF(E13<=0,"Additional funding requirement is £"&TEXT(ABS(E13),"#,##0")&"m below budget.","Additional funding requirement is £"&TEXT(E13,"#,##0")&"m above budget, highlighting increased external financing needs.") -> Additional funding requirement is £608m above budget, highlighting increased external financing needs.

Sheet 11_KPI_RATIOS
A1: KPI - NATIONAL GRID PLC
A3: KPI | B3: FY2024A | C3: FY2025A | D3: FY2026A | E3: FY2027E | F3: FY2028E | G3: FY2029E | H3: FY2030E | I3: FY2031E
A4: Revenue growth | B4: ="" | C4: ='05_INCOME_STATEMENT'!C6 -> -0.074156171 | D4: ='05_INCOME_STATEMENT'!D6 -> -0.037599304 | E4: ='05_INCOME_STATEMENT'!E6 -> 0.08 | F4: ='05_INCOME_STATEMENT'!F6 -> 0.07 | G4: ='05_INCOME_STATEMENT'!G6 -> 0.065 | H4: ='05_INCOME_STATEMENT'!H6 -> 0.06 | I4: ='05_INCOME_STATEMENT'!I6 -> 0.055
A5: Operating margin | B5: ='05_INCOME_STATEMENT'!B9 -> 0.22544081 | C5: ='05_INCOME_STATEMENT'!C9 -> 0.26847317 | D5: ='05_INCOME_STATEMENT'!D9 -> 0.30706168 | E5: ='05_INCOME_STATEMENT'!E9 -> 0.318 | F5: ='05_INCOME_STATEMENT'!F9 -> 0.32 | G5: ='05_INCOME_STATEMENT'!G9 -> 0.321 | H5: ='05_INCOME_STATEMENT'!H9 -> 0.322 | I5: ='05_INCOME_STATEMENT'!I9 -> 0.323
A6: PAT margin | B6: ='05_INCOME_STATEMENT'!B19/'05_INCOME_STATEMENT'!B5 -> 0.11168766 | C6: ='05_INCOME_STATEMENT'!C19/'05_INCOME_STATEMENT'!C5 -> 0.15393405 | D6: ='05_INCOME_STATEMENT'!D19/'05_INCOME_STATEMENT'!D5 -> 0.18335501 | E6: ='05_INCOME_STATEMENT'!E19/'05_INCOME_STATEMENT'!E5 -> 0.19243749 | F6: ='05_INCOME_STATEMENT'!F19/'05_INCOME_STATEMENT'!F5 -> 0.18573128 | G6: ='05_INCOME_STATEMENT'!G19/'05_INCOME_STATEMENT'!G5 -> 0.17840699 | H6: ='05_INCOME_STATEMENT'!H19/'05_INCOME_STATEMENT'!H5 -> 0.17378114 | I6: ='05_INCOME_STATEMENT'!I19/'05_INCOME_STATEMENT'!I5 -> 0.16977728
A7: Operating cash conversion | B7: ='07_CASH_FLOW'!B11/'05_INCOME_STATEMENT'!B8 -> 1.5506145 | C7: ='07_CASH_FLOW'!C11/'05_INCOME_STATEMENT'!C8 -> 1.3798135 | D7: ='07_CASH_FLOW'!D11/'05_INCOME_STATEMENT'!D8 -> 1.4415393 | E7: ='07_CASH_FLOW'!E11/'05_INCOME_STATEMENT'!E8 -> 1.5731993 | F7: ='07_CASH_FLOW'!F11/'05_INCOME_STATEMENT'!F8 -> 1.5683559 | G7: ='07_CASH_FLOW'!G11/'05_INCOME_STATEMENT'!G8 -> 1.5728035 | H7: ='07_CASH_FLOW'!H11/'05_INCOME_STATEMENT'!H8 -> 1.5731442 | I7: ='07_CASH_FLOW'!I11/'05_INCOME_STATEMENT'!I8 -> 1.5739192
A8: PP&E capex intensity | B8: =ABS('07_CASH_FLOW'!B13)/'05_INCOME_STATEMENT'!B5 -> 0.34780856 | C8: =ABS('07_CASH_FLOW'!C13)/'05_INCOME_STATEMENT'!C5 -> 0.47774513 | D8: =ABS('07_CASH_FLOW'!D13)/'05_INCOME_STATEMENT'!D5 -> 0.56476508 | E8: =ABS('07_CASH_FLOW'!E13)/'05_INCOME_STATEMENT'!E5 -> 0.61318315 | F8: =ABS('07_CASH_FLOW'!F13)/'05_INCOME_STATEMENT'!F5 -> 0.60833411 | G8: =ABS('07_CASH_FLOW'!G13)/'05_INCOME_STATEMENT'!G5 -> 0.58776242 | H8: =ABS('07_CASH_FLOW'!H13)/'05_INCOME_STATEMENT'!H5 -> 0.56230261 | I8: =ABS('07_CASH_FLOW'!I13)/'05_INCOME_STATEMENT'!I5 -> 0.54039087
A9: Cash flow after investing (£m) | B9: ='07_CASH_FLOW'!B11+'07_CASH_FLOW'!B15 -> -662 | C9: ='07_CASH_FLOW'!C11+'07_CASH_FLOW'!C15 -> -3785 | D9: ='07_CASH_FLOW'!D11+'07_CASH_FLOW'!D15 -> 3672 | E9: ='07_CASH_FLOW'!E11+'07_CASH_FLOW'!E15 -> -3102.4958 | F9: ='07_CASH_FLOW'!F11+'07_CASH_FLOW'!F15 -> -3179.2257 | G9: ='07_CASH_FLOW'!G11+'07_CASH_FLOW'!G15 -> -2846.4946 | H9: ='07_CASH_FLOW'!H11+'07_CASH_FLOW'!H15 -> -2367.2524 | I9: ='07_CASH_FLOW'!I11+'07_CASH_FLOW'!I15 -> -1898.921
A10: EBITDA proxy (£m) | B10: ='05_INCOME_STATEMENT'!B8+'07_CASH_FLOW'!B5 -> 6536 | C10: ='05_INCOME_STATEMENT'!C8+'07_CASH_FLOW'!C5 -> 7109 | D10: ='05_INCOME_STATEMENT'!D8+'07_CASH_FLOW'!D5 -> 7678 | E10: ='05_INCOME_STATEMENT'!E8+'07_CASH_FLOW'!E5 -> 8534.3875 | F10: ='05_INCOME_STATEMENT'!F8+'07_CASH_FLOW'!F5 -> 9269.7423 | G10: ='05_INCOME_STATEMENT'!G8+'07_CASH_FLOW'!G5 -> 9999.075 | H10: ='05_INCOME_STATEMENT'!H8+'07_CASH_FLOW'!H5 -> 10727.014 | I10: ='05_INCOME_STATEMENT'!I8+'07_CASH_FLOW'!I5 -> 11443.932
A11: Gross debt (£m) | B11: ='06_BALANCE_SHEET'!B21 -> 47072 | C11: ='06_BALANCE_SHEET'!C21 -> 47539 | D11: ='06_BALANCE_SHEET'!D21 -> 46755 | E11: ='06_BALANCE_SHEET'!E21 -> 53640.431 | F11: ='06_BALANCE_SHEET'!F21 -> 60851.989 | G11: ='06_BALANCE_SHEET'!G21 -> 68111.847 | H11: ='06_BALANCE_SHEET'!H21 -> 75238.521 | I11: ='06_BALANCE_SHEET'!I21 -> 82236.157
A12: Net debt (£m) | B12: ='06_BALANCE_SHEET'!B21-'06_BALANCE_SHEET'!B14 -> 46513 | C12: ='06_BALANCE_SHEET'!C21-'06_BALANCE_SHEET'!C14 -> 46361 | D12: ='06_BALANCE_SHEET'!D21-'06_BALANCE_SHEET'!D14 -> 46380 | E12: ='06_BALANCE_SHEET'!E21-'06_BALANCE_SHEET'!E14 -> 53140.431 | F12: ='06_BALANCE_SHEET'!F21-'06_BALANCE_SHEET'!F14 -> 60351.989 | G12: ='06_BALANCE_SHEET'!G21-'06_BALANCE_SHEET'!G14 -> 67611.847 | H12: ='06_BALANCE_SHEET'!H21-'06_BALANCE_SHEET'!H14 -> 74738.521 | I12: ='06_BALANCE_SHEET'!I21-'06_BALANCE_SHEET'!I14 -> 81736.157
A13: Net debt / EBITDA proxy | B13: =B12/B10 -> 7.1164321 | C13: =C12/C10 -> 6.5214517 | D13: =D12/D10 -> 6.0406356 | E13: =E12/E10 -> 6.226625 | F13: =F12/F10 -> 6.5106437 | G13: =G12/G10 -> 6.7618102 | H13: =H12/H10 -> 6.9673185 | I13: =I12/I10 -> 7.142314
A14: Interest coverage | B14: ='05_INCOME_STATEMENT'!B8/ABS('05_INCOME_STATEMENT'!B12) -> 2.6139019 | C14: ='05_INCOME_STATEMENT'!C8/ABS('05_INCOME_STATEMENT'!C12) -> 2.7304925 | D14: ='05_INCOME_STATEMENT'!D8/ABS('05_INCOME_STATEMENT'!D12) -> 3.1853372 | E14: ='05_INCOME_STATEMENT'!E8/ABS('05_INCOME_STATEMENT'!E12) -> 3.3376531 | F14: ='05_INCOME_STATEMENT'!F8/ABS('05_INCOME_STATEMENT'!F12) -> 3.0645585 | G14: ='05_INCOME_STATEMENT'!G8/ABS('05_INCOME_STATEMENT'!G12) -> 2.8270638 | H14: ='05_INCOME_STATEMENT'!H8/ABS('05_INCOME_STATEMENT'!H12) -> 2.697273 | I14: ='05_INCOME_STATEMENT'!I8/ABS('05_INCOME_STATEMENT'!I12) -> 2.5929912
A15: Debt / Equity | B15: ='06_BALANCE_SHEET'!B21/'06_BALANCE_SHEET'!B34 -> 1.5747357 | C15: ='06_BALANCE_SHEET'!C21/'06_BALANCE_SHEET'!C34 -> 1.2567811 | D15: ='06_BALANCE_SHEET'!D21/'06_BALANCE_SHEET'!D34 -> 1.1887872 | E15: ='06_BALANCE_SHEET'!E21/'06_BALANCE_SHEET'!E34 -> 1.3029653 | F15: ='06_BALANCE_SHEET'!F21/'06_BALANCE_SHEET'!F34 -> 1.4129919 | G15: ='06_BALANCE_SHEET'!G21/'06_BALANCE_SHEET'!G34 -> 1.5133341 | H15: ='06_BALANCE_SHEET'!H21/'06_BALANCE_SHEET'!H34 -> 1.6003874 | I15: ='06_BALANCE_SHEET'!I21/'06_BALANCE_SHEET'!I34 -> 1.6755835
A16: Receivables / Revenue | B16: ='06_BALANCE_SHEET'!B13/'05_INCOME_STATEMENT'!B5 -> 0.1720403 | C16: ='06_BALANCE_SHEET'!C13/'05_INCOME_STATEMENT'!C5 -> 0.22265753 | D16: ='06_BALANCE_SHEET'!D13/'05_INCOME_STATEMENT'!D5 -> 0.21863516 | E16: ='06_BALANCE_SHEET'!E13/'05_INCOME_STATEMENT'!E5 -> 0.215 | F16: ='06_BALANCE_SHEET'!F13/'05_INCOME_STATEMENT'!F5 -> 0.215 | G16: ='06_BALANCE_SHEET'!G13/'05_INCOME_STATEMENT'!G5 -> 0.215 | H16: ='06_BALANCE_SHEET'!H13/'05_INCOME_STATEMENT'!H5 -> 0.215 | I16: ='06_BALANCE_SHEET'!I13/'05_INCOME_STATEMENT'!I5 -> 0.215
A17: Payables / Revenue | B17: ='06_BALANCE_SHEET'!B22/'05_INCOME_STATEMENT'!B5 -> 0.20534005 | C17: ='06_BALANCE_SHEET'!C22/'05_INCOME_STATEMENT'!C5 -> 0.24333442 | D17: ='06_BALANCE_SHEET'!D22/'05_INCOME_STATEMENT'!D5 -> 0.2854639 | E17: ='06_BALANCE_SHEET'!E22/'05_INCOME_STATEMENT'!E5 -> 0.285 | F17: ='06_BALANCE_SHEET'!F22/'05_INCOME_STATEMENT'!F5 -> 0.285 | G17: ='06_BALANCE_SHEET'!G22/'05_INCOME_STATEMENT'!G5 -> 0.285 | H17: ='06_BALANCE_SHEET'!H22/'05_INCOME_STATEMENT'!H5 -> 0.285 | I17: ='06_BALANCE_SHEET'!I22/'05_INCOME_STATEMENT'!I5 -> 0.285
A18: ROA — closing assets basis | B18: ='05_INCOME_STATEMENT'!B19/'06_BALANCE_SHEET'!B18 -> 0.022547674 | C18: ='05_INCOME_STATEMENT'!C19/'06_BALANCE_SHEET'!C18 -> 0.026503157 | D18: ='05_INCOME_STATEMENT'!D19/'06_BALANCE_SHEET'!D18 -> 0.029949853 | E18: ='05_INCOME_STATEMENT'!E19/'06_BALANCE_SHEET'!E18 -> 0.030916956 | F18: ='05_INCOME_STATEMENT'!F19/'06_BALANCE_SHEET'!F18 -> 0.029215965 | G18: ='05_INCOME_STATEMENT'!G19/'06_BALANCE_SHEET'!G18 -> 0.027525382 | H18: ='05_INCOME_STATEMENT'!H19/'06_BALANCE_SHEET'!H18 -> 0.026350872 | I18: ='05_INCOME_STATEMENT'!I19/'06_BALANCE_SHEET'!I18 -> 0.0253277
A19: ROE — closing equity basis | B19: ='05_INCOME_STATEMENT'!B19/'06_BALANCE_SHEET'!B34 -> 0.074167001 | C19: ='05_INCOME_STATEMENT'!C19/'06_BALANCE_SHEET'!C34 -> 0.074789827 | D19: ='05_INCOME_STATEMENT'!D19/'06_BALANCE_SHEET'!D34 -> 0.08245614 | E19: ='05_INCOME_STATEMENT'!E19/'06_BALANCE_SHEET'!E34 -> 0.089291104 | F19: ='05_INCOME_STATEMENT'!F19/'06_BALANCE_SHEET'!F34 -> 0.088147835 | G19: ='05_INCOME_STATEMENT'!G19/'06_BALANCE_SHEET'!G34 -> 0.086285007 | H19: ='05_INCOME_STATEMENT'!H19/'06_BALANCE_SHEET'!H34 -> 0.085291292 | I19: ='05_INCOME_STATEMENT'!I19/'06_BALANCE_SHEET'!I34 -> 0.084207833
A20: Asset turnover | B20: ='05_INCOME_STATEMENT'!B5/'06_BALANCE_SHEET'!B18 -> 0.20188152 | C20: ='05_INCOME_STATEMENT'!C5/'06_BALANCE_SHEET'!C18 -> 0.17217215 | D20: ='05_INCOME_STATEMENT'!D5/'06_BALANCE_SHEET'!D18 -> 0.16334352 | E20: ='05_INCOME_STATEMENT'!E5/'06_BALANCE_SHEET'!E18 -> 0.16065974 | F20: ='05_INCOME_STATEMENT'!F5/'06_BALANCE_SHEET'!F18 -> 0.15730234 | G20: ='05_INCOME_STATEMENT'!G5/'06_BALANCE_SHEET'!G18 -> 0.15428421 | H20: ='05_INCOME_STATEMENT'!H5/'06_BALANCE_SHEET'!H18 -> 0.15163252 | I20: ='05_INCOME_STATEMENT'!I5/'06_BALANCE_SHEET'!I18 -> 0.14918192

Sheet 12_SCENARIOS
A1: SCENARIOS - NATIONAL GRID PLC
A3: Scenario Input | B3: Base | C3: Upside | D3: Downside
A4: Revenue growth | B4: 0.08 | C4: 0.1 | D4: 0.05
A5: Operating margin | B5: 0.318 | C5: 0.325 | D5: 0.305
A6: Capital investment (£m) | B6: 13000 | C6: 12500 | D6: 13500
A7: Effective interest rate | B7: 0.038 | C7: 0.035 | D7: 0.043
A8: Dividend payout ratio | B8: 0.5 | C8: 0.45 | D8: 0.5
A9: Minimum cash balance (£m) | B9: 500 | C9: 500 | D9: 500
A12: Scenario Output | B12: Base | C12: Upside | D12: Downside
A13: Revenue (£m) | B13: ='05_INCOME_STATEMENT'!D5*(1+B4) -> 19101.96 | C13: ='05_INCOME_STATEMENT'!D5*(1+C4) -> 19455.7 | D13: ='05_INCOME_STATEMENT'!D5*(1+D4) -> 18571.35
A14: Operating profit (£m) | B14: =B13*B5 -> 6074.4233 | C14: =C13*C5 -> 6323.1025 | D14: =D13*D5 -> 5664.2618
A15: PP&E additions (£m) | B15: =B6*'04_DRIVERS'!$C$16 -> 11713 | C15: =C6*'04_DRIVERS'!$C$16 -> 11262.5 | D15: =D6*'04_DRIVERS'!$C$16 -> 12163.5
A16: Depreciation (£m) | B16: ='06_BALANCE_SHEET'!$D$8*'04_DRIVERS'!$C$17 -> 2188.4342 | C16: ='06_BALANCE_SHEET'!$D$8*'04_DRIVERS'!$C$17 -> 2188.4342 | D16: ='06_BALANCE_SHEET'!$D$8*'04_DRIVERS'!$C$17 -> 2188.4342
A17: Base new borrowings (£m) | B17: =B6*'04_DRIVERS'!$C$19 -> 5200 | C17: =C6*'04_DRIVERS'!$C$19 -> 5000 | D17: =D6*'04_DRIVERS'!$C$19 -> 5400
A18: Debt repayments (£m) | B18: ='09_DEBT'!B9*6.25% -> 2922.1875 | C18: ='09_DEBT'!B9*6.25% -> 2922.1875 | D18: ='09_DEBT'!B9*6.25% -> 2922.1875
A19: Pre-funding closing debt (£m) | B19: ='09_DEBT'!B9+B17-B18 -> 49032.812 | C19: ='09_DEBT'!B9+C17-C18 -> 48832.812 | D19: ='09_DEBT'!B9+D17-D18 -> 49232.812
A20: Average debt (£m) | B20: =('09_DEBT'!B9+B19)/2 -> 47893.906 | C20: =('09_DEBT'!B9+C19)/2 -> 47793.906 | D20: =('09_DEBT'!B9+D19)/2 -> 47993.906
A21: Finance cost (£m) | B21: =B20*B7 -> 1819.9684 | C21: =C20*C7 -> 1672.7867 | D21: =D20*D7 -> 2063.738
A22: Profit before tax (£m) | B22: =B14+'05_INCOME_STATEMENT'!E11-B21+'05_INCOME_STATEMENT'!E13 -> 4712.7348 | C22: =C14+'05_INCOME_STATEMENT'!F11-C21+'05_INCOME_STATEMENT'!F13 -> 5110.9442 | D22: =D14+'05_INCOME_STATEMENT'!G11-D21+'05_INCOME_STATEMENT'!G13 -> 4063.571
A23: Profit after tax (£m) | B23: =B22*(1-'04_DRIVERS'!$C$8) -> 3675.9332 | C23: =C22*(1-'04_DRIVERS'!$C$8) -> 3986.5365 | D23: =D22*(1-'04_DRIVERS'!$C$8) -> 3169.5854
A24: Dividend (£m) | B24: =-B23*B8 -> -1837.9666 | C24: =-C23*C8 -> -1793.9414 | D24: =-D23*D8 -> -1584.7927
A26: Cash Flow Scenario | B26: Base | C26: Upside | D26: Downside
A27: Inventory (£m) | B27: =B13*'04_DRIVERS'!$B$25 -> 611.26272 | C27: =C13*'04_DRIVERS'!$B$25 -> 622.5824 | D27: =D13*'04_DRIVERS'!$B$25 -> 594.2832
A28: Receivables (£m) | B28: =B13*'04_DRIVERS'!$B$26 -> 4106.9214 | C28: =C13*'04_DRIVERS'!$B$26 -> 4182.9755 | D28: =D13*'04_DRIVERS'!$B$26 -> 3992.8403
A29: Payables (£m) | B29: =B13*'04_DRIVERS'!$B$27 -> 5444.0586 | C29: =C13*'04_DRIVERS'!$B$27 -> 5544.8745 | D29: =D13*'04_DRIVERS'!$B$27 -> 5292.8347
A30: Contract liabilities (£m) | B30: ='06_BALANCE_SHEET'!D23*(1+'04_DRIVERS'!$B$31) -> 3005.63 | C30: ='06_BALANCE_SHEET'!D23*(1+'04_DRIVERS'!$B$31) -> 3005.63 | D30: ='06_BALANCE_SHEET'!D23*(1+'04_DRIVERS'!$B$31) -> 3005.63
A31: Working capital movement (£m) | B31: =-(B27-'06_BALANCE_SHEET'!D12)-(B28-'06_BALANCE_SHEET'!D13)+(B29-'06_BALANCE_SHEET'!D22)+(B30-'06_BALANCE_SHEET'!D23) -> 299.50448 | C31: =-(C27-'06_BALANCE_SHEET'!D12)-(C28-'06_BALANCE_SHEET'!D13)+(C29-'06_BALANCE_SHEET'!D22)+(C30-'06_BALANCE_SHEET'!D23) -> 312.9466 | D31: =-(D27-'06_BALANCE_SHEET'!D12)-(D28-'06_BALANCE_SHEET'!D13)+(D29-'06_BALANCE_SHEET'!D22)+(D30-'06_BALANCE_SHEET'!D23) -> 279.3413
A32: Provisions movement (£m) | B32: ='06_BALANCE_SHEET'!D25*'04_DRIVERS'!$B$33 -> 62.42 | C32: ='06_BALANCE_SHEET'!D25*'04_DRIVERS'!$B$33 -> 62.42 | D32: ='06_BALANCE_SHEET'!D25*'04_DRIVERS'!$B$33 -> 62.42
A33: Closing PP&E (£m) | B33: ='06_BALANCE_SHEET'!D8+B15-B16 -> 91044.566 | C33: ='06_BALANCE_SHEET'!D8+C15-C16 -> 90594.066 | D33: ='06_BALANCE_SHEET'!D8+D15-D16 -> 91495.066
A34: Deferred tax liability (£m) | B34: =B33*'04_DRIVERS'!$B$32 -> 10105.947 | C34: =C33*'04_DRIVERS'!$B$32 -> 10055.941 | D34: =D33*'04_DRIVERS'!$B$32 -> 10155.952
A35: Other liabilities (£m) | B35: =B13*'04_DRIVERS'!$B$34 -> 2349.5411 | C35: =C13*'04_DRIVERS'!$B$34 -> 2393.0511 | D35: =D13*'04_DRIVERS'!$B$34 -> 2284.2761
A36: Other operating adjustments (£m) | B36: ='05_INCOME_STATEMENT'!$E$11+'05_INCOME_STATEMENT'!$E$13+(B34-'06_BALANCE_SHEET'!$D$24)+(B35-'06_BALANCE_SHEET'!$D$26) -> 1696.7679 | C36: ='05_INCOME_STATEMENT'!$E$11+'05_INCOME_STATEMENT'!$E$13+(C34-'06_BALANCE_SHEET'!$D$24)+(C35-'06_BALANCE_SHEET'!$D$26) -> 1690.2724 | D36: ='05_INCOME_STATEMENT'!$E$11+'05_INCOME_STATEMENT'!$E$13+(D34-'06_BALANCE_SHEET'!$D$24)+(D35-'06_BALANCE_SHEET'!$D$26) -> 1681.5084
A37: D&A (£m) | B37: =B16+('06_BALANCE_SHEET'!$D$7*'04_DRIVERS'!$B$38) -> 2459.9642 | C37: =C16+('06_BALANCE_SHEET'!$D$7*'04_DRIVERS'!$B$38) -> 2459.9642 | D37: =D16+('06_BALANCE_SHEET'!$D$7*'04_DRIVERS'!$B$38) -> 2459.9642
A38: Tax paid (£m) | B38: =-B22*'04_DRIVERS'!$C$8 -> -1036.8017 | C38: =-C22*'04_DRIVERS'!$C$8 -> -1124.4077 | D38: =-D22*'04_DRIVERS'!$C$8 -> -893.98563
A39: Net operating cash flow (£m) | B39: =B14+B37+B31+B32+B36+B38 -> 9556.2782 | C39: =C14+C37+C31+C32+C36+C38 -> 9724.298 | D39: =D14+D37+D31+D32+D36+D38 -> 9253.51
A41: Investing Scenario | B41: Base | C41: Upside | D41: Downside
A42: Closing intangible assets (£m) | B42: ='06_BALANCE_SHEET'!D7*(1+'04_DRIVERS'!$B$29) -> 4072.95 | C42: ='06_BALANCE_SHEET'!D7*(1+'04_DRIVERS'!$B$29) -> 4072.95 | D42: ='06_BALANCE_SHEET'!D7*(1+'04_DRIVERS'!$B$29) -> 4072.95
A43: Intangible purchases (£m) | B43: =-((B42-'06_BALANCE_SHEET'!D7)+('06_BALANCE_SHEET'!D7*'04_DRIVERS'!$B$38)) -> -465.48 | C43: =-((C42-'06_BALANCE_SHEET'!D7)+('06_BALANCE_SHEET'!D7*'04_DRIVERS'!$B$38)) -> -465.48 | D43: =-((D42-'06_BALANCE_SHEET'!D7)+('06_BALANCE_SHEET'!D7*'04_DRIVERS'!$B$38)) -> -465.48
A44: PP&E purchases (£m) | B44: =-B15 -> -11713 | C44: =-C15 -> -11262.5 | D44: =-D15 -> -12163.5
A45: Other investing cash flows (£m) | B45: =-(('06_BALANCE_SHEET'!D9*(1+'04_DRIVERS'!$B$30))-'06_BALANCE_SHEET'!D9)-(B13*'04_DRIVERS'!$B$28-'06_BALANCE_SHEET'!D15) -> -480.294 | C45: =-(('06_BALANCE_SHEET'!D9*(1+'04_DRIVERS'!$B$30))-'06_BALANCE_SHEET'!D9)-(C13*'04_DRIVERS'!$B$28-'06_BALANCE_SHEET'!D15) -> -533.355 | D45: =-(('06_BALANCE_SHEET'!D9*(1+'04_DRIVERS'!$B$30))-'06_BALANCE_SHEET'!D9)-(D13*'04_DRIVERS'!$B$28-'06_BALANCE_SHEET'!D15) -> -400.7025
A46: Net investing cash flow (£m) | B46: =SUM(B43:B45) -> -12658.774 | C46: =SUM(C43:C45) -> -12261.335 | D46: =SUM(D43:D45) -> -13029.682
A48: Funding & Leverage | B48: Base | C48: Upside | D48: Downside
A49: Cash before additional funding (£m) | B49: ='06_BALANCE_SHEET'!D14+B39+B46+B17-B18-B21+B24 -> -4107.6183 | C49: ='06_BALANCE_SHEET'!D14+C39+C46+C17-C18-C21+C24 -> -3550.9526 | D49: ='06_BALANCE_SHEET'!D14+D39+D46+D17-D18-D21+D24 -> -4571.8907
A50: Additional liquidity funding (£m) | B50: =MAX(0,B9-B49) -> 4607.6183 | C50: =MAX(0,C9-C49) -> 4050.9526 | D50: =MAX(0,D9-D49) -> 5071.8907
A51: Ending cash (£m) | B51: =B49+B50 -> 500 | C51: =C49+C50 -> 500 | D51: =D49+D50 -> 500
A52: Closing gross debt (£m) | B52: ='09_DEBT'!B9+B17+B50-B18 -> 53640.431 | C52: ='09_DEBT'!B9+C17+C50-C18 -> 52883.765 | D52: ='09_DEBT'!B9+D17+D50-D18 -> 54304.703
A53: Net debt (£m) | B53: =B52-B51 -> 53140.431 | C53: =C52-C51 -> 52383.765 | D53: =D52-D51 -> 53804.703
A54: EBITDA proxy (£m) | B54: =B14+B37 -> 8534.3875 | C54: =C14+C37 -> 8783.0667 | D54: =D14+D37 -> 8124.226
A55: Net debt / EBITDA | B55: =B53/B54 -> 6.226625 | C55: =C53/C54 -> 5.9641771 | D55: =D53/D54 -> 6.6227482
A56: Interest coverage | B56: =B14/B21 -> 3.3376531 | C56: =C14/C21 -> 3.7799813 | D56: =D14/D21 -> 2.7446613

Sheet 13_DCF_VALUATION
A1: DCF VALUATION - NATIONAL GRID PLC
A3: DCF ASSUMPTIONS | B3: Value
A4: WACC | B4: 0.05
A5: Terminal growth rate | B5: 0.025
A6: Terminal ROIC | B6: 0.065
A7: FY2026 Net debt (£m) | B7: ='06_BALANCE_SHEET'!D21-'06_BALANCE_SHEET'!D14 -> 46380
A8: Diluted shares outstanding (m) | B8: 4971
A9: Market price reference (p) | B9: 1150.5
A10: Valuation date | B10: 46269
A12: FCFF FORECAST | B12: FY2027E | C12: FY2028E | D12: FY2029E | E12: FY2030E | F12: FY2031E
A13: Operating profit / EBIT (£m) | B13: ='05_INCOME_STATEMENT'!E8 -> 6074.4233 | C13: ='05_INCOME_STATEMENT'!F8 -> 6540.5111 | D13: ='05_INCOME_STATEMENT'!G8 -> 6987.412 | E13: ='05_INCOME_STATEMENT'!H8 -> 7429.7304 | F13: ='05_INCOME_STATEMENT'!I8 -> 7862.7083
A14: Tax rate | B14: ='05_INCOME_STATEMENT'!E16 -> 0.22 | C14: ='05_INCOME_STATEMENT'!F16 -> 0.22 | D14: ='05_INCOME_STATEMENT'!G16 -> 0.22 | E14: ='05_INCOME_STATEMENT'!H16 -> 0.22 | F14: ='05_INCOME_STATEMENT'!I16 -> 0.22
A15: NOPAT (£m) | B15: =B13*(1-B14) -> 4738.0502 | C15: =C13*(1-C14) -> 5101.5987 | D15: =D13*(1-D14) -> 5450.1813 | E15: =E13*(1-E14) -> 5795.1897 | F15: =F13*(1-F14) -> 6132.9125
A16: D&A (£m) | B16: ='07_CASH_FLOW'!E5 -> 2459.9642 | C16: ='07_CASH_FLOW'!F5 -> 2729.2312 | D16: ='07_CASH_FLOW'!G5 -> 3011.663 | E16: ='07_CASH_FLOW'!H5 -> 3297.2833 | F16: ='07_CASH_FLOW'!I5 -> 3581.2239
A17: Working capital movement (£m) | B17: ='07_CASH_FLOW'!E6 -> 299.50448 | C17: ='07_CASH_FLOW'!F6 -> 261.20531 | D17: ='07_CASH_FLOW'!G6 -> 275.60626 | E17: ='07_CASH_FLOW'!H6 -> 290.51042 | F17: ='07_CASH_FLOW'!I6 -> 305.96585
A18: Provisions / pensions movement (£m) | B18: ='07_CASH_FLOW'!E7 -> 62.42 | C18: ='07_CASH_FLOW'!F7 -> 63.6684 | D18: ='07_CASH_FLOW'!G7 -> 64.941768 | E18: ='07_CASH_FLOW'!H7 -> 66.240603 | F18: ='07_CASH_FLOW'!I7 -> 67.565415
A19: Deferred tax movement (£m) | B19: ='06_BALANCE_SHEET'!E24-'06_BALANCE_SHEET'!D24 -> 1065.9468 | C19: ='06_BALANCE_SHEET'!F24-'06_BALANCE_SHEET'!E24 -> 1108.854 | D19: ='06_BALANCE_SHEET'!G24-'06_BALANCE_SHEET'!F24 -> 1119.0908 | E19: ='06_BALANCE_SHEET'!H24-'06_BALANCE_SHEET'!G24 -> 1109.0506 | F19: ='06_BALANCE_SHEET'!I24-'06_BALANCE_SHEET'!H24 -> 1099.2799
A20: Other liabilities movement (£m) | B20: ='06_BALANCE_SHEET'!E26-'06_BALANCE_SHEET'!D26 -> 172.54108 | C20: ='06_BALANCE_SHEET'!F26-'06_BALANCE_SHEET'!E26 -> 164.46788 | D20: ='06_BALANCE_SHEET'!G26-'06_BALANCE_SHEET'!F26 -> 163.41058 | E20: ='06_BALANCE_SHEET'!H26-'06_BALANCE_SHEET'!G26 -> 160.64517 | F20: ='06_BALANCE_SHEET'!I26-'06_BALANCE_SHEET'!H26 -> 156.09356
A21: Net investing cash flow (£m) | B21: ='07_CASH_FLOW'!E15 -> -12658.774 | C21: ='07_CASH_FLOW'!F15 -> -13437.075 | D21: ='07_CASH_FLOW'!G15 -> -13836.32 | E21: ='07_CASH_FLOW'!H15 -> -14055.29 | F21: ='07_CASH_FLOW'!I15 -> -14274.188
A22: FCFF (£m) | B22: =SUM(B15:B20)+B21 -> -3860.3473 | C22: =SUM(C15:C20)+C21 -> -4008.0492 | D22: =SUM(D15:D20)+D21 -> -3751.4267 | E22: =SUM(E15:E20)+E21 -> -3336.3701 | F22: =SUM(F15:F20)+F21 -> -2931.1471
A23: Discount period | B23: 1 | C23: 2 | D23: 3 | E23: 4 | F23: 5
A24: Discount factor | B24: =1/(1+$B$4)^B23 -> 0.95238095 | C24: =1/(1+$B$4)^C23 -> 0.90702948 | D24: =1/(1+$B$4)^D23 -> 0.8638376 | E24: =1/(1+$B$4)^E23 -> 0.82270247 | F24: =1/(1+$B$4)^F23 -> 0.78352617
A25: PV of FCFF (£m) | B25: =B22*B24 -> -3676.5212 | C25: =C22*C24 -> -3635.4188 | D25: =D22*D24 -> -3240.6234 | E25: =E22*E24 -> -2744.8399 | F25: =F22*F24 -> -2296.6305
A28: TERMINAL VALUE | B28: Value
A29: FY2031 NOPAT (£m) | B29: =F15 -> 6132.9125
A30: Terminal growth rate | B30: =$B$5 -> 0.025
A31: Terminal ROIC | B31: =$B$6 -> 0.065
A32: Terminal reinvestment rate | B32: =B30/B31 -> 0.38461538
A33: Normalised terminal FCFF (£m) | B33: =B29*(1-B32) -> 3774.1
A34: Terminal value (£m) | B34: =B33*(1+B30)/($B$4-B30) -> 154738.1
A35: PV of terminal value (£m) | B35: =B34/(1+$B$4)^5 -> 121241.35
A36: PV of explicit FCFF (£m) | B36: =SUM(B25:F25) -> -15594.034
A37: Enterprise value (£m) | B37: =B35+B36 -> 105647.32
A38: Less: FY2026 net debt (£m) | B38: =-$B$7 -> -46380
A39: Equity value (£m) | B39: =B37+B38 -> 59267.316
A40: Diluted shares outstanding (m) | B40: =$B$8 -> 4971
A41: Implied value per share (£) | B41: =B39/B40 -> 11.922614
A42: Implied value per share (p) | B42: =B41*100 -> 1192.2614
A43: Market price reference (p) | B43: =$B$9 -> 1150.5
A44: Upside / (Downside) | B44: =B42/B43-1 -> 0.03629851
A48: DCF SENSITIVITY — IMPLIED SHARE PRICE (p)
A49: Terminal Growth / WACC | B49: 0.045 | C49: 0.0475 | D49: 0.05 | E49: 0.0525 | F49: 0.055
A50: 0.02 | B50: {=((SUMPRODUCT($B$22:$F$22,1/(1+B$49)^$B$23:$F$23)+((($F$15*(1-$A50/$B$6))*(1+$A50)/(B$49-$A50))/(1+B$49)^5)-$B$7)/$B$8*100)} -> 1545.5226 | C50: {=((SUMPRODUCT($B$22:$F$22,1/(1+C$49)^$B$23:$F$23)+((($F$15*(1-$A50/$B$6))*(1+$A50)/(C$49-$A50))/(1+C$49)^5)-$B$7)/$B$8*100)} -> 1263.2106 | D50: {=((SUMPRODUCT($B$22:$F$22,1/(1+D$49)^$B$23:$F$23)+((($F$15*(1-$A50/$B$6))*(1+$A50)/(D$49-$A50))/(1+D$49)^5)-$B$7)/$B$8*100)} -> 1028.6718 | E50: {=((SUMPRODUCT($B$22:$F$22,1/(1+E$49)^$B$23:$F$23)+((($F$15*(1-$A50/$B$6))*(1+$A50)/(E$49-$A50))/(1+E$49)^5)-$B$7)/$B$8*100)} -> 830.87068 | F50: {=((SUMPRODUCT($B$22:$F$22,1/(1+F$49)^$B$23:$F$23)+((($F$15*(1-$A50/$B$6))*(1+$A50)/(F$49-$A50))/(1+F$49)^5)-$B$7)/$B$8*100)} -> 661.92508
A51: 0.0225 | B51: {=((SUMPRODUCT($B$22:$F$22,1/(1+B$49)^$B$23:$F$23)+((($F$15*(1-$A51/$B$6))*(1+$A51)/(B$49-$A51))/(1+B$49)^5)-$B$7)/$B$8*100)} -> 1690.8094 | C51: {=((SUMPRODUCT($B$22:$F$22,1/(1+C$49)^$B$23:$F$23)+((($F$15*(1-$A51/$B$6))*(1+$A51)/(C$49-$A51))/(1+C$49)^5)-$B$7)/$B$8*100)} -> 1367.2958 | D51: {=((SUMPRODUCT($B$22:$F$22,1/(1+D$49)^$B$23:$F$23)+((($F$15*(1-$A51/$B$6))*(1+$A51)/(D$49-$A51))/(1+D$49)^5)-$B$7)/$B$8*100)} -> 1103.3687 | E51: {=((SUMPRODUCT($B$22:$F$22,1/(1+E$49)^$B$23:$F$23)+((($F$15*(1-$A51/$B$6))*(1+$A51)/(E$49-$A51))/(1+E$49)^5)-$B$7)/$B$8*100)} -> 884.12012 | F51: {=((SUMPRODUCT($B$22:$F$22,1/(1+F$49)^$B$23:$F$23)+((($F$15*(1-$A51/$B$6))*(1+$A51)/(F$49-$A51))/(1+F$49)^5)-$B$7)/$B$8*100)} -> 699.22927
A52: 0.025 | B52: {=((SUMPRODUCT($B$22:$F$22,1/(1+B$49)^$B$23:$F$23)+((($F$15*(1-$A52/$B$6))*(1+$A52)/(B$49-$A52))/(1+B$49)^5)-$B$7)/$B$8*100)} -> 1871.4659 | C52: {=((SUMPRODUCT($B$22:$F$22,1/(1+C$49)^$B$23:$F$23)+((($F$15*(1-$A52/$B$6))*(1+$A52)/(C$49-$A52))/(1+C$49)^5)-$B$7)/$B$8*100)} -> 1493.6748 | D52: {=((SUMPRODUCT($B$22:$F$22,1/(1+D$49)^$B$23:$F$23)+((($F$15*(1-$A52/$B$6))*(1+$A52)/(D$49-$A52))/(1+D$49)^5)-$B$7)/$B$8*100)} -> 1192.2614 | E52: {=((SUMPRODUCT($B$22:$F$22,1/(1+E$49)^$B$23:$F$23)+((($F$15*(1-$A52/$B$6))*(1+$A52)/(E$49-$A52))/(1+E$49)^5)-$B$7)/$B$8*100)} -> 946.38329 | F52: {=((SUMPRODUCT($B$22:$F$22,1/(1+F$49)^$B$23:$F$23)+((($F$15*(1-$A52/$B$6))*(1+$A52)/(F$49-$A52))/(1+F$49)^5)-$B$7)/$B$8*100)} -> 742.14571
A53: 0.0275 | B53: {=((SUMPRODUCT($B$22:$F$22,1/(1+B$49)^$B$23:$F$23)+((($F$15*(1-$A53/$B$6))*(1+$A53)/(B$49-$A53))/(1+B$49)^5)-$B$7)/$B$8*100)} -> 2102.6506 | C53: {=((SUMPRODUCT($B$22:$F$22,1/(1+C$49)^$B$23:$F$23)+((($F$15*(1-$A53/$B$6))*(1+$A53)/(C$49-$A53))/(1+C$49)^5)-$B$7)/$B$8*100)} -> 1650.708 | D53: {=((SUMPRODUCT($B$22:$F$22,1/(1+D$49)^$B$23:$F$23)+((($F$15*(1-$A53/$B$6))*(1+$A53)/(D$49-$A53))/(1+D$49)^5)-$B$7)/$B$8*100)} -> 1300.0819 | E53: {=((SUMPRODUCT($B$22:$F$22,1/(1+E$49)^$B$23:$F$23)+((($F$15*(1-$A53/$B$6))*(1+$A53)/(E$49-$A53))/(1+E$49)^5)-$B$7)/$B$8*100)} -> 1020.3643 | F53: {=((SUMPRODUCT($B$22:$F$22,1/(1+F$49)^$B$23:$F$23)+((($F$15*(1-$A53/$B$6))*(1+$A53)/(F$49-$A53))/(1+F$49)^5)-$B$7)/$B$8*100)} -> 792.20501
A54: 0.03 | B54: {=((SUMPRODUCT($B$22:$F$22,1/(1+B$49)^$B$23:$F$23)+((($F$15*(1-$A54/$B$6))*(1+$A54)/(B$49-$A54))/(1+B$49)^5)-$B$7)/$B$8*100)} -> 2409.6276 | C54: {=((SUMPRODUCT($B$22:$F$22,1/(1+C$49)^$B$23:$F$23)+((($F$15*(1-$A54/$B$6))*(1+$A54)/(C$49-$A54))/(1+C$49)^5)-$B$7)/$B$8*100)} -> 1851.5329 | D54: {=((SUMPRODUCT($B$22:$F$22,1/(1+D$49)^$B$23:$F$23)+((($F$15*(1-$A54/$B$6))*(1+$A54)/(D$49-$A54))/(1+D$49)^5)-$B$7)/$B$8*100)} -> 1433.928 | E54: {=((SUMPRODUCT($B$22:$F$22,1/(1+E$49)^$B$23:$F$23)+((($F$15*(1-$A54/$B$6))*(1+$A54)/(E$49-$A54))/(1+E$49)^5)-$B$7)/$B$8*100)} -> 1109.9691 | F54: {=((SUMPRODUCT($B$22:$F$22,1/(1+F$49)^$B$23:$F$23)+((($F$15*(1-$A54/$B$6))*(1+$A54)/(F$49-$A54))/(1+F$49)^5)-$B$7)/$B$8*100)} -> 851.55005

Sheet 14_DASHBOARD
A1: NATIONAL GRID — FINANCIAL ANALYSIS | P1: HELPER DATA — keep with dashboard when copying
A2: FY2024A–FY2031E | Base Case | £m unless stated
P3: Year | Q3: Revenue (£m) | R3: Operating Profit (£m) | T3: Year | U3: Gross Debt (£m) | V3: Additional Funding (£m) | X3: Scenario | Y3: Additional Funding (£m)
P4: FY2024A | Q4: 19850 | R4: 4475 | T4: FY2026A | U4: 46755 | V4: 0 | X4: Base | Y4: 4607.62
A5: £19.1bn | D5: 31.8% | G5: £53.6bn | J5: 6.2x | M5: 1,192p | P5: FY2025A | Q5: 18378 | R5: 4934 | T5: FY2027E | U5: 53640.43 | V5: 4607.62 | X5: Upside | Y5: 4050.95
T6: FY2028E | U6: 60851.99 | V6: 5044.08 | X6: Downside | Y6: 5071.89
A7: FY2027 Revenue | D7: Operating Margin | G7: FY2027 Gross Debt | J7: Net Debt / EBITDA | M7: DCF Value / Share | T7: FY2029E | U7: 68111.85 | V7: 5383.11
T8: FY2030E | U8: 75238.52 | V8: 5623.66
T9: FY2031E | U9: 82236.16 | V9: 5860.04
A26: £3.7bn | D26: £13.0bn | G26: £4.6bn | J26: 3.3x
A29: FY2027 Profit After Tax | D29: FY2027 Capital Investment | G29: Additional Funding | J29: Interest Coverage
H33: 1,150.5p | K33: +3.6% | M33: £82.2bn
H36: Market Price | K36: DCF Upside | M36: FY2031 Gross Debt

Sheet 15_CHECKS 
A1: NATIONAL GRID PLC — MODEL INTEGRITY CHECKS
A4: OVERALL STATUS | C4: TOTAL CHECKS | D4: PASSED | E4: FAILED | F4: MODEL ERROR
A5: =IF(D5=C5,"PASS","FAIL") -> PASS | C5: =COUNTA(A9:A24) -> 16 | D5: =COUNTIF(F9:F24,"PASS") -> 16 | E5: =COUNTIF(F9:F24,"FAIL") -> 0 | F5: =SUM(D9:D24) -> 6.184564e-11
A8: ID | B8: Model Area | C8: Integrity Check | D8: Difference / Error | E8: Tolerance | F8: Status | G8: Purpose
A9: CHK-01 | B9: Balance Sheet | C9: Total Assets = Total Liabilities & Equity | D9: =ABS('[1]06_BALANCE_SHEET'!B18-'[1]06_BALANCE_SHEET'!B36)+ABS('[1]06_BALANCE_SHEET'!C18-'[1]06_BALANCE_SHEET'!C36)+ABS('[1]06_BALANCE_SHEET'!D18-'[1]06_BALANCE_SHEET'!D36)+ABS('[1]06_BALANCE_SHEET'!E18-'[1]06_BALANCE_SHEET'!E36)+ABS('[1]06_BALANCE_SHEET'!F18-'[1]06_BALANCE_SHEET'!F36)+ABS('[1]06_BALANCE_SHEET'!G18-'[1]06_BALANCE_SHEET'!G36)+ABS('[1]06_BALANCE_SHEET'!H18-'[1]06_BALANCE_SHEET'!H36)+ABS('[1]06_BALANCE_SHEET'!I18-'[1]06_BALANCE_SHEET'!I36) -> 5.8207661e-11 | E9: 0.1 | F9: =IF(ABS(D9)<=E9,"PASS","FAIL") -> PASS | G9: Confirms the balance sheet balances across all historical and forecast years.
A10: CHK-02 | B10: Cash Flow | C10: Opening Cash + Net Change + FX = Ending Cash | D10: =ABS('[1]07_CASH_FLOW'!B23+'[1]07_CASH_FLOW'!B24+'[1]07_CASH_FLOW'!B25-'[1]07_CASH_FLOW'!B26)+ABS('[1]07_CASH_FLOW'!C23+'[1]07_CASH_FLOW'!C24+'[1]07_CASH_FLOW'!C25-'[1]07_CASH_FLOW'!C26)+ABS('[1]07_CASH_FLOW'!D23+'[1]07_CASH_FLOW'!D24+'[1]07_CASH_FLOW'!D25-'[1]07_CASH_FLOW'!D26)+ABS('[1]07_CASH_FLOW'!E23+'[1]07_CASH_FLOW'!E24+'[1]07_CASH_FLOW'!E25-'[1]07_CASH_FLOW'!E26)+ABS('[1]07_CASH_FLOW'!F23+'[1]07_CASH_FLOW'!F24+'[1]07_CASH_FLOW'!F25-'[1]07_CASH_FLOW'!F26)+ABS('[1]07_CASH_FLOW'!G23+'[1]07_CASH_FLOW'!G24+'[1]07_CASH_FLOW'!G25-'[1]07_CASH_FLOW'!G26)+ABS('[1]07_CASH_FLOW'!H23+'[1]07_CASH_FLOW'!H24+'[1]07_CASH_FLOW'!H25-'[1]07_CASH_FLOW'!H26)+ABS('[1]07_CASH_FLOW'!I23+'[1]07_CASH_FLOW'!I24+'[1]07_CASH_FLOW'!I25-'[1]07_CASH_FLOW'!I26) -> 0 | E10: 0.1 | F10: =IF(ABS(D10)<=E10,"PASS","FAIL") -> PASS | G10: Confirms the cash roll-forward is mathematically consistent.
A11: CHK-03 | B11: 3-Statement Link | C11: Cash Flow ending cash = Balance Sheet cash | D11: =ABS('[1]07_CASH_FLOW'!B26-'[1]06_BALANCE_SHEET'!B14)+ABS('[1]07_CASH_FLOW'!C26-'[1]06_BALANCE_SHEET'!C14)+ABS('[1]07_CASH_FLOW'!D26-'[1]06_BALANCE_SHEET'!D14)+ABS('[1]07_CASH_FLOW'!E26-'[1]06_BALANCE_SHEET'!E14)+ABS('[1]07_CASH_FLOW'!F26-'[1]06_BALANCE_SHEET'!F14)+ABS('[1]07_CASH_FLOW'!G26-'[1]06_BALANCE_SHEET'!G14)+ABS('[1]07_CASH_FLOW'!H26-'[1]06_BALANCE_SHEET'!H14)+ABS('[1]07_CASH_FLOW'!I26-'[1]06_BALANCE_SHEET'!I14) -> 0 | E11: 0.1 | F11: =IF(ABS(D11)<=E11,"PASS","FAIL") -> PASS | G11: Checks that the cash flow statement links correctly into the balance sheet.
A12: CHK-04 | B12: PP&E Schedule | C12: Opening PP&E + Additions - Depreciation + Other = Closing PP&E | D12: =ABS('[1]08_CAPEX_PPE'!B5+'[1]08_CAPEX_PPE'!B6-'[1]08_CAPEX_PPE'!B7+'[1]08_CAPEX_PPE'!B8-'[1]08_CAPEX_PPE'!B9)+ABS('[1]08_CAPEX_PPE'!C5+'[1]08_CAPEX_PPE'!C6-'[1]08_CAPEX_PPE'!C7+'[1]08_CAPEX_PPE'!C8-'[1]08_CAPEX_PPE'!C9)+ABS('[1]08_CAPEX_PPE'!D5+'[1]08_CAPEX_PPE'!D6-'[1]08_CAPEX_PPE'!D7+'[1]08_CAPEX_PPE'!D8-'[1]08_CAPEX_PPE'!D9)+ABS('[1]08_CAPEX_PPE'!E5+'[1]08_CAPEX_PPE'!E6-'[1]08_CAPEX_PPE'!E7+'[1]08_CAPEX_PPE'!E8-'[1]08_CAPEX_PPE'!E9)+ABS('[1]08_CAPEX_PPE'!F5+'[1]08_CAPEX_PPE'!F6-'[1]08_CAPEX_PPE'!F7+'[1]08_CAPEX_PPE'!F8-'[1]08_CAPEX_PPE'!F9)+ABS('[1]08_CAPEX_PPE'!G5+'[1]08_CAPEX_PPE'!G6-'[1]08_CAPEX_PPE'!G7+'[1]08_CAPEX_PPE'!G8-'[1]08_CAPEX_PPE'!G9) -> 0 | E12: 0.1 | F12: =IF(ABS(D12)<=E12,"PASS","FAIL") -> PASS | G12: Validates the PP&E roll-forward schedule.
A13: CHK-05 | B13: PP&E / Balance Sheet | C13: PP&E schedule closing balance = Balance Sheet PP&E | D13: =ABS('[1]08_CAPEX_PPE'!B9-'[1]06_BALANCE_SHEET'!D8)+ABS('[1]08_CAPEX_PPE'!C9-'[1]06_BALANCE_SHEET'!E8)+ABS('[1]08_CAPEX_PPE'!D9-'[1]06_BALANCE_SHEET'!F8)+ABS('[1]08_CAPEX_PPE'!E9-'[1]06_BALANCE_SHEET'!G8)+ABS('[1]08_CAPEX_PPE'!F9-'[1]06_BALANCE_SHEET'!H8)+ABS('[1]08_CAPEX_PPE'!G9-'[1]06_BALANCE_SHEET'!I8) -> 0 | E13: 0.1 | F13: =IF(ABS(D13)<=E13,"PASS","FAIL") -> PASS | G13: Confirms the supporting PP&E schedule ties to the balance sheet.
A14: CHK-06 | B14: Debt Schedule | C14: Opening Debt + Borrowings - Repayments + Other + Funding = Closing Debt | D14: =ABS('[1]09_DEBT'!B5+'[1]09_DEBT'!B6-'[1]09_DEBT'!B7+'[1]09_DEBT'!B8+'[1]09_DEBT'!B14-'[1]09_DEBT'!B9)+ABS('[1]09_DEBT'!C5+'[1]09_DEBT'!C6-'[1]09_DEBT'!C7+'[1]09_DEBT'!C8+'[1]09_DEBT'!C14-'[1]09_DEBT'!C9)+ABS('[1]09_DEBT'!D5+'[1]09_DEBT'!D6-'[1]09_DEBT'!D7+'[1]09_DEBT'!D8+'[1]09_DEBT'!D14-'[1]09_DEBT'!D9)+ABS('[1]09_DEBT'!E5+'[1]09_DEBT'!E6-'[1]09_DEBT'!E7+'[1]09_DEBT'!E8+'[1]09_DEBT'!E14-'[1]09_DEBT'!E9)+ABS('[1]09_DEBT'!F5+'[1]09_DEBT'!F6-'[1]09_DEBT'!F7+'[1]09_DEBT'!F8+'[1]09_DEBT'!F14-'[1]09_DEBT'!F9)+ABS('[1]09_DEBT'!G5+'[1]09_DEBT'!G6-'[1]09_DEBT'!G7+'[1]09_DEBT'!G8+'[1]09_DEBT'!G14-'[1]09_DEBT'!G9) -> 0 | E14: 0.1 | F14: =IF(ABS(D14)<=E14,"PASS","FAIL") -> PASS | G14: Validates the debt roll-forward including additional liquidity funding.
A15: CHK-07 | B15: Debt / Balance Sheet | C15: Debt schedule closing debt = Balance Sheet borrowings | D15: =ABS('[1]09_DEBT'!B9-'[1]06_BALANCE_SHEET'!D21)+ABS('[1]09_DEBT'!C9-'[1]06_BALANCE_SHEET'!E21)+ABS('[1]09_DEBT'!D9-'[1]06_BALANCE_SHEET'!F21)+ABS('[1]09_DEBT'!E9-'[1]06_BALANCE_SHEET'!G21)+ABS('[1]09_DEBT'!F9-'[1]06_BALANCE_SHEET'!H21)+ABS('[1]09_DEBT'!G9-'[1]06_BALANCE_SHEET'!I21) -> 0 | E15: 0.1 | F15: =IF(ABS(D15)<=E15,"PASS","FAIL") -> PASS | G15: Confirms debt schedule balances feed correctly into the balance sheet.
A16: CHK-08 | B16: Debt / Income Statement | C16: Debt schedule finance cost = Income Statement finance cost | D16: =ABS('[1]09_DEBT'!B13+'[1]05_INCOME_STATEMENT'!D12)+ABS('[1]09_DEBT'!C13+'[1]05_INCOME_STATEMENT'!E12)+ABS('[1]09_DEBT'!D13+'[1]05_INCOME_STATEMENT'!F12)+ABS('[1]09_DEBT'!E13+'[1]05_INCOME_STATEMENT'!G12)+ABS('[1]09_DEBT'!F13+'[1]05_INCOME_STATEMENT'!H12)+ABS('[1]09_DEBT'!G13+'[1]05_INCOME_STATEMENT'!I12) -> 0 | E16: 0.1 | F16: =IF(ABS(D16)<=E16,"PASS","FAIL") -> PASS | G16: Checks that calculated debt interest expense ties to the income statement.
A17: CHK-09 | B17: Income Statement | C17: Profit Before Tax + Tax Expense = Profit After Tax | D17: =ABS('[1]05_INCOME_STATEMENT'!B15+'[1]05_INCOME_STATEMENT'!B17-'[1]05_INCOME_STATEMENT'!B19)+ABS('[1]05_INCOME_STATEMENT'!C15+'[1]05_INCOME_STATEMENT'!C17-'[1]05_INCOME_STATEMENT'!C19)+ABS('[1]05_INCOME_STATEMENT'!D15+'[1]05_INCOME_STATEMENT'!D17-'[1]05_INCOME_STATEMENT'!D19)+ABS('[1]05_INCOME_STATEMENT'!E15+'[1]05_INCOME_STATEMENT'!E17-'[1]05_INCOME_STATEMENT'!E19)+ABS('[1]05_INCOME_STATEMENT'!F15+'[1]05_INCOME_STATEMENT'!F17-'[1]05_INCOME_STATEMENT'!F19)+ABS('[1]05_INCOME_STATEMENT'!G15+'[1]05_INCOME_STATEMENT'!G17-'[1]05_INCOME_STATEMENT'!G19)+ABS('[1]05_INCOME_STATEMENT'!H15+'[1]05_INCOME_STATEMENT'!H17-'[1]05_INCOME_STATEMENT'!H19)+ABS('[1]05_INCOME_STATEMENT'!I15+'[1]05_INCOME_STATEMENT'!I17-'[1]05_INCOME_STATEMENT'!I19) -> 0 | E17: 0.1 | F17: =IF(ABS(D17)<=E17,"PASS","FAIL") -> PASS | G17: Validates the income statement tax and profit bridge.
A18: CHK-10 | B18: Income Statement | C18: Revenue × Operating Margin = Operating Profit | D18: =ABS('[1]05_INCOME_STATEMENT'!B5*'[1]05_INCOME_STATEMENT'!B9-'[1]05_INCOME_STATEMENT'!B8)+ABS('[1]05_INCOME_STATEMENT'!C5*'[1]05_INCOME_STATEMENT'!C9-'[1]05_INCOME_STATEMENT'!C8)+ABS('[1]05_INCOME_STATEMENT'!D5*'[1]05_INCOME_STATEMENT'!D9-'[1]05_INCOME_STATEMENT'!D8)+ABS('[1]05_INCOME_STATEMENT'!E5*'[1]05_INCOME_STATEMENT'!E9-'[1]05_INCOME_STATEMENT'!E8)+ABS('[1]05_INCOME_STATEMENT'!F5*'[1]05_INCOME_STATEMENT'!F9-'[1]05_INCOME_STATEMENT'!F8)+ABS('[1]05_INCOME_STATEMENT'!G5*'[1]05_INCOME_STATEMENT'!G9-'[1]05_INCOME_STATEMENT'!G8)+ABS('[1]05_INCOME_STATEMENT'!H5*'[1]05_INCOME_STATEMENT'!H9-'[1]05_INCOME_STATEMENT'!H8)+ABS('[1]05_INCOME_STATEMENT'!I5*'[1]05_INCOME_STATEMENT'!I9-'[1]05_INCOME_STATEMENT'!I8) -> 9.094947e-13 | E18: 0.1 | F18: =IF(ABS(D18)<=E18,"PASS","FAIL") -> PASS | G18: Confirms operating margin calculations are internally consistent.
A19: CHK-11 | B19: Equity | C19: Opening Equity + PAT + Dividends + Other = Closing Equity | D19: =ABS('[1]06_BALANCE_SHEET'!C30+'[1]06_BALANCE_SHEET'!C31+'[1]06_BALANCE_SHEET'!C32+'[1]06_BALANCE_SHEET'!C33-'[1]06_BALANCE_SHEET'!C34)+ABS('[1]06_BALANCE_SHEET'!D30+'[1]06_BALANCE_SHEET'!D31+'[1]06_BALANCE_SHEET'!D32+'[1]06_BALANCE_SHEET'!D33-'[1]06_BALANCE_SHEET'!D34)+ABS('[1]06_BALANCE_SHEET'!E30+'[1]06_BALANCE_SHEET'!E31+'[1]06_BALANCE_SHEET'!E32+'[1]06_BALANCE_SHEET'!E33-'[1]06_BALANCE_SHEET'!E34)+ABS('[1]06_BALANCE_SHEET'!F30+'[1]06_BALANCE_SHEET'!F31+'[1]06_BALANCE_SHEET'!F32+'[1]06_BALANCE_SHEET'!F33-'[1]06_BALANCE_SHEET'!F34)+ABS('[1]06_BALANCE_SHEET'!G30+'[1]06_BALANCE_SHEET'!G31+'[1]06_BALANCE_SHEET'!G32+'[1]06_BALANCE_SHEET'!G33-'[1]06_BALANCE_SHEET'!G34)+ABS('[1]06_BALANCE_SHEET'!H30+'[1]06_BALANCE_SHEET'!H31+'[1]06_BALANCE_SHEET'!H32+'[1]06_BALANCE_SHEET'!H33-'[1]06_BALANCE_SHEET'!H34)+ABS('[1]06_BALANCE_SHEET'!I30+'[1]06_BALANCE_SHEET'!I31+'[1]06_BALANCE_SHEET'!I32+'[1]06_BALANCE_SHEET'!I33-'[1]06_BALANCE_SHEET'!I34) -> 0 | E19: 0.1 | F19: =IF(ABS(D19)<=E19,"PASS","FAIL") -> PASS | G19: Validates the shareholders' equity roll-forward.
A20: CHK-12 | B20: Scenarios | C20: Base Scenario outputs tie to FY2027 Base Forecast | D20: =ABS('[1]12_SCENARIOS'!B13-'[1]05_INCOME_STATEMENT'!E5)+ABS('[1]12_SCENARIOS'!B14-'[1]05_INCOME_STATEMENT'!E8)+ABS('[1]12_SCENARIOS'!B23-'[1]05_INCOME_STATEMENT'!E19)+ABS('[1]12_SCENARIOS'!B51-'[1]07_CASH_FLOW'!E26)+ABS('[1]12_SCENARIOS'!B52-'[1]09_DEBT'!C9)+ABS('[1]12_SCENARIOS'!B55-'[1]11_KPI_RATIOS'!E13)+ABS('[1]12_SCENARIOS'!B56-'[1]11_KPI_RATIOS'!E14) -> 4.5474735e-13 | E20: 0.1 | F20: =IF(ABS(D20)<=E20,"PASS","FAIL") -> PASS | G20: Confirms the Base scenario is consistent with the core FY2027 forecast.
A21: CHK-13 | B21: DCF | C21: Enterprise Value = PV Explicit FCFF + PV Terminal Value | D21: =ABS('[1]13_DCF_VALUATION'!B37-('[1]13_DCF_VALUATION'!B35+'[1]13_DCF_VALUATION'!B36)) -> 0 | E21: 0.1 | F21: =IF(ABS(D21)<=E21,"PASS","FAIL") -> PASS | G21: Checks the core DCF enterprise value bridge.
A22: CHK-14 | B22: DCF | C22: Equity Value = Enterprise Value - Net Debt | D22: =ABS('[1]13_DCF_VALUATION'!B39-('[1]13_DCF_VALUATION'!B37+'[1]13_DCF_VALUATION'!B38)) -> 0 | E22: 0.1 | F22: =IF(ABS(D22)<=E22,"PASS","FAIL") -> PASS | G22: Confirms the enterprise-to-equity value bridge.
A23: CHK-15 | B23: DCF | C23: Implied Share Price = Equity Value / Diluted Shares | D23: =ABS('[1]13_DCF_VALUATION'!B42-('[1]13_DCF_VALUATION'!B39/'[1]13_DCF_VALUATION'!B40*100)) -> 0 | E23: 0.1 | F23: =IF(ABS(D23)<=E23,"PASS","FAIL") -> PASS | G23: Validates the implied value per share calculation in pence.
A24: CHK-16 | B24: Liquidity | C24: Forecast Ending Cash = Minimum Cash Assumption | D24: =ABS('[1]07_CASH_FLOW'!E26-'[1]04_DRIVERS'!$B$37)+ABS('[1]07_CASH_FLOW'!F26-'[1]04_DRIVERS'!$B$37)+ABS('[1]07_CASH_FLOW'!G26-'[1]04_DRIVERS'!$B$37)+ABS('[1]07_CASH_FLOW'!H26-'[1]04_DRIVERS'!$B$37)+ABS('[1]07_CASH_FLOW'!I26-'[1]04_DRIVERS'!$B$37) -> 2.2737368e-12 | E24: 0.1 | F24: =IF(ABS(D24)<=E24,"PASS","FAIL") -> PASS | G24: Confirms forecast liquidity funding maintains the modelled minimum cash balance.
